<?xml version="1.0" encoding="UTF-8"?>
<jobs><Job><jobTitle>技术培训生</jobTitle><jobSaray>5-10K/月</jobSaray><jobDemand>广州市 本科 应届生</jobDemand><commpanyName>广州西洋汇信息技术有限公司</commpanyName><commpanyDesc>办公环境好 福利好 技术氛围浓厚 发展空间大</commpanyDesc><posCount>3个职位</posCount></Job><Job><jobTitle>开发工程师（PHP）</jobTitle><jobSaray>6-12K/月</jobSaray><jobDemand>广州市 本科 1-3年</jobDemand><commpanyName>广州西洋汇信息技术有限公司</commpanyName><commpanyDesc>办公环境好 发展空间大 福利好 技术氛围浓厚</commpanyDesc><posCount>3个职位</posCount></Job><Job><jobTitle>前端工程师</jobTitle><jobSaray>10-16K/月</jobSaray><jobDemand>广州市 本科 1-3年</jobDemand><commpanyName>广州西洋汇信息技术有限公司</commpanyName><commpanyDesc>办公环境好 发展空间大 福利好 技术氛围浓厚</commpanyDesc><posCount>3个职位</posCount></Job><Job><jobTitle>算法优化工程师</jobTitle><jobSaray>15-30K/月</jobSaray><jobDemand>深圳市 本科 3-5年</jobDemand><commpanyName>深圳晶泰科技有限公司</commpanyName><commpanyDesc>扁平化管理 竞争性薪酬福利 云计算大牛团队</commpanyDesc><posCount>3个职位</posCount></Job><Job><jobTitle>高级算法工程师</jobTitle><jobSaray>15-30K/月</jobSaray><jobDemand>深圳市 本科 1-3年</jobDemand><commpanyName>深圳晶泰科技有限公司</commpanyName><commpanyDesc>扁平化管理 竞争性薪酬福利 云计算大牛团队</commpanyDesc><posCount>3个职位</posCount></Job><Job><jobTitle>资深前端开发工程师</jobTitle><jobSaray>15-25K/月</jobSaray><jobDemand>深圳市 本科 3-5年</jobDemand><commpanyName>深圳晶泰科技有限公司</commpanyName><commpanyDesc>扁平化管理 竞争性薪酬福利 云计算大牛团队</commpanyDesc><posCount>3个职位</posCount></Job><Job><jobTitle>PHP架构师</jobTitle><jobSaray>15-25K/月</jobSaray><jobDemand>青岛市 大专 5-10年</jobDemand><commpanyName>青岛英杰联智企业管理咨询有限公司</commpanyName><commpanyDesc>无</commpanyDesc><posCount>3个职位</posCount></Job><Job><jobTitle>IOS架构师</jobTitle><jobSaray>15-25K/月</jobSaray><jobDemand>青岛市 大专 5-10年</jobDemand><commpanyName>青岛英杰联智企业管理咨询有限公司</commpanyName><commpanyDesc>无</commpanyDesc><posCount>3个职位</posCount></Job><Job><jobTitle>Android架构师</jobTitle><jobSaray>15-25K/月</jobSaray><jobDemand>青岛市 大专 5-10年</jobDemand><commpanyName>青岛英杰联智企业管理咨询有限公司</commpanyName><commpanyDesc>无</commpanyDesc><posCount>3个职位</posCount></Job><Job><jobTitle>.Net工程师</jobTitle><jobSaray>15-25K/月</jobSaray><jobDemand>深圳市 大专 3-5年</jobDemand><commpanyName>优利科技有限公司（U-TECHNOLOGY SERVICES LIMITED）</commpanyName><commpanyDesc>无</commpanyDesc><posCount>3个职位</posCount></Job><Job><jobTitle>前端工程师</jobTitle><jobSaray>15-25K/月</jobSaray><jobDemand>深圳市 大专 1-3年</jobDemand><commpanyName>优利科技有限公司（U-TECHNOLOGY SERVICES LIMITED）</commpanyName><commpanyDesc>无</commpanyDesc><posCount>3个职位</posCount></Job><Job><jobTitle>Java工程师</jobTitle><jobSaray>15-25K/月</jobSaray><jobDemand>深圳市 大专 3-5年</jobDemand><commpanyName>优利科技有限公司（U-TECHNOLOGY SERVICES LIMITED）</commpanyName><commpanyDesc>无</commpanyDesc><posCount>3个职位</posCount></Job><Job><jobTitle>Android开发工程师</jobTitle><jobSaray>8-13K/月</jobSaray><jobDemand>广州市 本科 1-3年</jobDemand><commpanyName>广州冰鸟网络科技有限公司</commpanyName><commpanyDesc>福利活动多多 50元-天餐补 年底双薪 绩效奖金 五险一金</commpanyDesc><posCount>4个职位</posCount></Job><Job><jobTitle>高级数据开发工程师</jobTitle><jobSaray>15-20K/月</jobSaray><jobDemand>广州市 本科 3-5年</jobDemand><commpanyName>广州冰鸟网络科技有限公司</commpanyName><commpanyDesc>50元-天餐补 福利活动多多 绩效奖金 年底双薪 五险一金</commpanyDesc><posCount>4个职位</posCount></Job><Job><jobTitle>淘宝-新制造 JAVA开发工程师</jobTitle><jobSaray>15-30K/月</jobSaray><jobDemand>杭州市 本科 3-5年</jobDemand><commpanyName>阿里巴巴集团</commpanyName><commpanyDesc>尊重个人发展意愿 有竞争力的薪酬 优秀人才阿里股票</commpanyDesc><posCount>52个职位</posCount></Job><Job><jobTitle>3D主美</jobTitle><jobSaray>15-30K/月</jobSaray><jobDemand>成都市 大专 5-10年</jobDemand><commpanyName>成都市晓易互动科技有限公司</commpanyName><commpanyDesc>不定期旅游 定期体检 全勤奖 社保公积金 周末双休</commpanyDesc><posCount>9个职位</posCount></Job><Job><jobTitle>U3D客户端主程</jobTitle><jobSaray>15-20K/月</jobSaray><jobDemand>成都市 本科 3-5年</jobDemand><commpanyName>成都市晓易互动科技有限公司</commpanyName><commpanyDesc>不定期旅游 定期体检 全勤奖 社保公积金 周末双休</commpanyDesc><posCount>9个职位</posCount></Job><Job><jobTitle>PHP高级开发工程师</jobTitle><jobSaray>10-15K/月</jobSaray><jobDemand>成都市 本科 3-5年</jobDemand><commpanyName>成都市晓易互动科技有限公司</commpanyName><commpanyDesc>不定期旅游 定期体检 全勤奖 社保公积金 周末双休</commpanyDesc><posCount>9个职位</posCount></Job><Job><jobTitle>数值策划组组长</jobTitle><jobSaray>10-14K/月</jobSaray><jobDemand>成都市 本科 3-5年</jobDemand><commpanyName>成都市晓易互动科技有限公司</commpanyName><commpanyDesc>不定期旅游 定期体检 全勤奖 社保公积金 周末双休</commpanyDesc><posCount>9个职位</posCount></Job><Job><jobTitle>服务器主程（Python）</jobTitle><jobSaray>20-25K/月</jobSaray><jobDemand>成都市 本科 5-10年</jobDemand><commpanyName>成都市晓易互动科技有限公司</commpanyName><commpanyDesc>不定期旅游 定期体检 全勤奖 社保公积金 周末双休</commpanyDesc><posCount>9个职位</posCount></Job><Job><jobTitle>手游美宣</jobTitle><jobSaray>7-10K/月</jobSaray><jobDemand>成都市 本科 1-3年</jobDemand><commpanyName>成都市晓易互动科技有限公司</commpanyName><commpanyDesc>不定期旅游 定期体检 全勤奖 社保公积金 周末双休</commpanyDesc><posCount>9个职位</posCount></Job><Job><jobTitle>架构师</jobTitle><jobSaray>25-50K/月</jobSaray><jobDemand>深圳市 本科 5-10年</jobDemand><commpanyName>深圳智慧园区信息技术有限公司</commpanyName><commpanyDesc>扁平化管理 发展前景好</commpanyDesc><posCount>2个职位</posCount></Job><Job><jobTitle>Web前端工程师</jobTitle><jobSaray>10-20K/月</jobSaray><jobDemand>深圳市 大专 3-5年</jobDemand><commpanyName>深圳智慧园区信息技术有限公司</commpanyName><commpanyDesc>扁平化管理 发展前景好</commpanyDesc><posCount>2个职位</posCount></Job><Job><jobTitle>底层资深研发工程师</jobTitle><jobSaray>30-60K/月</jobSaray><jobDemand>北京市 本科 3-5年</jobDemand><commpanyName>北京一会儿科技有限公司</commpanyName><commpanyDesc>风口行业-大牛云集</commpanyDesc><posCount>1个职位</posCount></Job><Job><jobTitle>JAVA开发师</jobTitle><jobSaray>10-20K/月</jobSaray><jobDemand>武汉市 大专 3-5年</jobDemand><commpanyName>武汉艾能进咨询管理顾问有限公司</commpanyName><commpanyDesc>所做项目-电商平台</commpanyDesc><posCount>7个职位</posCount></Job><Job><jobTitle>JAVA高级开发工程师</jobTitle><jobSaray>10-20K/月</jobSaray><jobDemand>武汉市 本科 3-5年</jobDemand><commpanyName>武汉艾能进咨询管理顾问有限公司</commpanyName><commpanyDesc>无</commpanyDesc><posCount>7个职位</posCount></Job><Job><jobTitle>中级C#开发工程师</jobTitle><jobSaray>10-20K/月</jobSaray><jobDemand>武汉市 本科 3-5年 武汉艾能进咨询管理顾问有限公司 7个职位 2018-07-03更新</jobDemand><commpanyName>武汉艾能进咨询管理顾问有限公司</commpanyName><commpanyDesc>无</commpanyDesc><posCount>7个职位</posCount></Job><Job><jobTitle>硬件工程师</jobTitle><jobSaray>10-20K/月</jobSaray><jobDemand>武汉市 本科 3-5年</jobDemand><commpanyName>武汉艾能进咨询管理顾问有限公司</commpanyName><commpanyDesc>无</commpanyDesc><posCount>7个职位</posCount></Job><Job><jobTitle>系统工程师</jobTitle><jobSaray>10-20K/月</jobSaray><jobDemand>武汉市 本科 3-5年</jobDemand><commpanyName>武汉艾能进咨询管理顾问有限公司</commpanyName><commpanyDesc>无</commpanyDesc><posCount>7个职位</posCount></Job><Job><jobTitle>系统分析师</jobTitle><jobSaray>10-20K/月</jobSaray><jobDemand>武汉市 本科 3-5年</jobDemand><commpanyName>武汉艾能进咨询管理顾问有限公司</commpanyName><commpanyDesc>无</commpanyDesc><posCount>7个职位</posCount></Job><Job><jobTitle>Flash开发工程师（AS3）</jobTitle><jobSaray>15-30K/月</jobSaray><jobDemand>上海市 本科 3-5年</jobDemand><commpanyName>孤岛（上海）软件有限公司</commpanyName><commpanyDesc>餐饮补贴 股票期权 交通补贴 五险一金 住宿补贴</commpanyDesc><posCount>10个职位</posCount></Job><Job><jobTitle>UE4程序</jobTitle><jobSaray>20-40K/月</jobSaray><jobDemand>上海市 本科 3-5年</jobDemand><commpanyName>孤岛（上海）软件有限公司</commpanyName><commpanyDesc>餐饮补贴 股票期权 交通补贴 五险一金 住宿补贴</commpanyDesc><posCount>10个职位</posCount></Job><Job><jobTitle>U3D引擎专家</jobTitle><jobSaray>30-60K/月</jobSaray><jobDemand>上海市 本科 5-10年</jobDemand><commpanyName>孤岛（上海）软件有限公司</commpanyName><commpanyDesc>餐饮补贴 股票期权 交通补贴 五险一金 住宿补贴</commpanyDesc><posCount>10个职位</posCount></Job><Job><jobTitle>前端开发工程师</jobTitle><jobSaray>9-15K/月</jobSaray><jobDemand>北京市 本科 1-3年</jobDemand><commpanyName>北京立思辰电子系统技术有限公司</commpanyName><commpanyDesc>成长空间大 团队Nice 团队建设 年终奖金</commpanyDesc><posCount>2个职位</posCount></Job><Job><jobTitle>IT Account Manager</jobTitle><jobSaray>18-25K/月</jobSaray><jobDemand>上海市 本科 3-5年</jobDemand><commpanyName>首旅如家酒店集团</commpanyName><commpanyDesc>带薪病假 年底多薪 带薪年假 补充医疗保险</commpanyDesc><posCount>4个职位</posCount></Job><Job><jobTitle>.NET开发工程师</jobTitle><jobSaray>10-15K/月</jobSaray><jobDemand>上海市 本科 应届生</jobDemand><commpanyName>首旅如家酒店集团</commpanyName><commpanyDesc>补充医疗 带薪年假 年底多薪</commpanyDesc><posCount>4个职位</posCount></Job><Job><jobTitle>IT网络工程师</jobTitle><jobSaray>10-15K/月</jobSaray><jobDemand>上海市 大专 5-10年</jobDemand><commpanyName>首旅如家酒店集团</commpanyName><commpanyDesc>补充医疗 带薪年假 年底多薪</commpanyDesc><posCount>4个职位</posCount></Job><Job><jobTitle>前端工程师</jobTitle><jobSaray>15-25K/月</jobSaray><jobDemand>北京市 本科 3-5年</jobDemand><commpanyName>北京微名天下科技有限公司</commpanyName><commpanyDesc>无</commpanyDesc><posCount>1个职位</posCount></Job><Job><jobTitle>Android驱动工程师</jobTitle><jobSaray>10-14K/月</jobSaray><jobDemand>广州市 本科 3-5年</jobDemand><commpanyName>广州信位通讯科技有限公司</commpanyName><commpanyDesc>年度旅游 绩效奖金 五险一金</commpanyDesc><posCount>4个职位</posCount></Job><Job><jobTitle>嵌入式软件工程师（边缘计算网关）</jobTitle><jobSaray>15-25K/月</jobSaray><jobDemand>北京市 硕士 3-5年</jobDemand><commpanyName>北京龙鼎源科技股份有限公司技术开发中心</commpanyName><commpanyDesc>优秀研发团队 补充医疗保险 五险一金 弹性工作制</commpanyDesc><posCount>2个职位</posCount></Job><Job><jobTitle>射频工程师</jobTitle><jobSaray>10-14K/月</jobSaray><jobDemand>广州市 本科 3-5年</jobDemand><commpanyName>广州信位通讯科技有限公司</commpanyName><commpanyDesc>绩效奖金 年度旅游 五险一金</commpanyDesc><posCount>4个职位</posCount></Job><Job><jobTitle>嵌入式软件工程师（功能安全产品）</jobTitle><jobSaray>15-25K/月</jobSaray><jobDemand>北京市 硕士 3-5年</jobDemand><commpanyName>北京龙鼎源科技股份有限公司技术开发中心</commpanyName><commpanyDesc>优秀研发团队 补充医疗保险 五险一金 弹性工作制 20天带薪年假</commpanyDesc><posCount>2个职位</posCount></Job><Job><jobTitle>嵌入式软件工程师</jobTitle><jobSaray>7-12K/月</jobSaray><jobDemand>广州市 本科 1-3年</jobDemand><commpanyName>广州信位通讯科技有限公司</commpanyName><commpanyDesc>绩效奖金 年度旅游 五险一金</commpanyDesc><posCount>4个职位</posCount></Job><Job><jobTitle>Android应用工程师</jobTitle><jobSaray>7-13K/月</jobSaray><jobDemand>广州市 本科 3-5年</jobDemand><commpanyName>广州信位通讯科技有限公司</commpanyName><commpanyDesc>年度旅游 绩效奖金 五险一金</commpanyDesc><posCount>4个职位</posCount></Job><Job><jobTitle>iOS开发（高级）工程师 - 独立闭环业...</jobTitle><jobSaray>20-40K/月</jobSaray><jobDemand>上海市 本科 3-5年</jobDemand><commpanyName>北京字节跳动网络技术有限公司</commpanyName><commpanyDesc>免费三餐 悠闲下午茶 优秀团队 租房补贴-带薪休假</commpanyDesc><posCount>26个职位</posCount></Job><Job><jobTitle>Java/Scala开发工程师</jobTitle><jobSaray>13-20K/月</jobSaray><jobDemand>南京市 本科 3-5年</jobDemand><commpanyName>南京领添信息技术有限公司</commpanyName><commpanyDesc>五险一金-双休-大牛</commpanyDesc><posCount>6个职位</posCount></Job><Job><jobTitle>Java开发工程师（中级）</jobTitle><jobSaray>13-18K/月</jobSaray><jobDemand>南京市 本科 3-5年</jobDemand><commpanyName>南京领添信息技术有限公司</commpanyName><commpanyDesc>五险一金-双休-大牛</commpanyDesc><posCount>6个职位</posCount></Job><Job><jobTitle>PHP开发工程师</jobTitle><jobSaray>13-18K/月</jobSaray><jobDemand>南京市 本科 3-5年</jobDemand><commpanyName></commpanyName><commpanyDesc>五险一金-双休-大牛</commpanyDesc><posCount>6个职位</posCount></Job><Job><jobTitle>数据仓库工程师</jobTitle><jobSaray>15-30K/月</jobSaray><jobDemand>南京市 本科 3-5年</jobDemand><commpanyName>南京领添信息技术有限公司</commpanyName><commpanyDesc>五险一金-双休-大牛</commpanyDesc><posCount>6个职位</posCount></Job><Job><jobTitle>算法工程师</jobTitle><jobSaray>15-30K/月</jobSaray><jobDemand>南京市 本科 1-3年</jobDemand><commpanyName>南京领添信息技术有限公司</commpanyName><commpanyDesc>无</commpanyDesc><posCount>6个职位</posCount></Job><Job><jobTitle>前端高级开发工程师</jobTitle><jobSaray>15-24K/月</jobSaray><jobDemand>深圳市 本科 3-5年</jobDemand><commpanyName>深圳市神盾信息技术有限公司</commpanyName><commpanyDesc>五险一金 年底双薪</commpanyDesc><posCount>4个职位</posCount></Job><Job><jobTitle>软件开发实习生(可留用)</jobTitle><jobSaray>2-4K/月</jobSaray><jobDemand>上海市 本科 应届生</jobDemand><commpanyName>首旅如家酒店集团</commpanyName><commpanyDesc>午餐补助 优秀团队 公司规模大 可留用</commpanyDesc><posCount>4个职位</posCount></Job><Job><jobTitle>测试开发实习生</jobTitle><jobSaray>3-4K/月</jobSaray><jobDemand>北京市 本科 应届生</jobDemand><commpanyName>APP ANNIE</commpanyName><commpanyDesc>工程师文化 技术成长大 国际化团队</commpanyDesc><posCount>4个职位</posCount></Job><Job><jobTitle>后端开发实习生</jobTitle><jobSaray>3-4K/月</jobSaray><jobDemand>北京市 本科 应届生</jobDemand><commpanyName>APP ANNIE</commpanyName><commpanyDesc>国际互团队 大数据分析 移动互联网 工程师文化</commpanyDesc><posCount>4个职位</posCount></Job><Job><jobTitle>H5前端开发工程师</jobTitle><jobSaray>15-30K/月</jobSaray><jobDemand>北京市 本科 3-5年</jobDemand><commpanyName>北京立思辰电子系统技术有限公司</commpanyName><commpanyDesc>五险一金 团队建设 年终奖金 团队Nice 成长空间大</commpanyDesc><posCount>2个职位</posCount></Job><Job><jobTitle>Python Server Engine...</jobTitle><jobSaray>15-20K/月</jobSaray><jobDemand>深圳市 本科 1-3年</jobDemand><commpanyName>睿初科技（深圳）有限公司</commpanyName><commpanyDesc>无</commpanyDesc><posCount>6个职位</posCount></Job><Job><jobTitle>IOS/Android开发工程师</jobTitle><jobSaray>10-20K/月</jobSaray><jobDemand>武汉市 本科 3-5年</jobDemand><commpanyName>武汉艾能进咨询管理顾问有限公司</commpanyName><commpanyDesc>无</commpanyDesc><posCount>7个职位</posCount></Job><Job><jobTitle>Windows客户端开发</jobTitle><jobSaray>15-20K/月</jobSaray><jobDemand>武汉市 本科 3-5年</jobDemand><commpanyName>武汉诸相网络科技有限公司</commpanyName><commpanyDesc>无</commpanyDesc><posCount>3个职位</posCount></Job><Job><jobTitle>资深PHP开发</jobTitle><jobSaray>15-25K/月</jobSaray><jobDemand>武汉市 本科 5-10年</jobDemand><commpanyName>武汉诸相网络科技有限公司</commpanyName><commpanyDesc>无</commpanyDesc><posCount>3个职位</posCount></Job><Job><jobTitle>资深前端</jobTitle><jobSaray>20-30K/月</jobSaray><jobDemand>武汉市 本科 5-10年</jobDemand><commpanyName>武汉诸相网络科技有限公司</commpanyName><commpanyDesc>无</commpanyDesc><posCount>3个职位</posCount></Job><Job><jobTitle>资深Java开发（运满满）</jobTitle><jobSaray>20-40K/月</jobSaray><jobDemand>南京市 本科 3-5年</jobDemand><commpanyName>北京满运物流信息有限公司</commpanyName><commpanyDesc>E轮融资 五险一金 行业独角兽 优秀团队</commpanyDesc><posCount>3个职位</posCount></Job><Job><jobTitle>数据挖掘工程师</jobTitle><jobSaray>15-30K/月</jobSaray><jobDemand>北京市 本科 1-3年</jobDemand><commpanyName>上海韬轶企业管理咨询有限公司</commpanyName><commpanyDesc>技术驱动公司 精英团队 海量数据-风控平台</commpanyDesc><posCount>1个职位</posCount></Job><Job><jobTitle>Java开发工程师</jobTitle><jobSaray>15-25K/月</jobSaray><jobDemand>北京市 本科 3-5年</jobDemand><commpanyName>北京多贝兄弟信息技术有限公司</commpanyName><commpanyDesc>不打卡 极客氛围 免费午餐 六险一金</commpanyDesc><posCount>10个职位</posCount></Job><Job><jobTitle>测试工程师</jobTitle><jobSaray>10-20K/月</jobSaray><jobDemand>北京市 本科 1-3年</jobDemand><commpanyName>北京多贝兄弟信息技术有限公司</commpanyName><commpanyDesc>不打卡 极客氛围 免费午餐 六险一金</commpanyDesc><posCount>10个职位</posCount></Job><Job><jobTitle>自动化测试工程师</jobTitle><jobSaray>15-25K/月</jobSaray><jobDemand>北京市 本科 1-3年</jobDemand><commpanyName>北京多贝兄弟信息技术有限公司</commpanyName><commpanyDesc>不打卡 极客氛围 免费午餐 六险一金</commpanyDesc><posCount>10个职位</posCount></Job><Job><jobTitle>运维工程师</jobTitle><jobSaray>10-20K/月</jobSaray><jobDemand>北京市 本科 1-3年</jobDemand><commpanyName>北京多贝兄弟信息技术有限公司</commpanyName><commpanyDesc>不打卡 极客氛围 免费午餐 六险一金</commpanyDesc><posCount>10个职位</posCount></Job><Job><jobTitle>Linux C/C++开发工程师</jobTitle><jobSaray>20-30K/月</jobSaray><jobDemand>北京市 本科 1-3年</jobDemand><commpanyName>北京多贝兄弟信息技术有限公司</commpanyName><commpanyDesc>不打卡 极客氛围 免费午餐 六险一金</commpanyDesc><posCount>10个职位</posCount></Job><Job><jobTitle>Web前端工程师</jobTitle><jobSaray>15-25K/月</jobSaray><jobDemand>北京市 本科 1-3年</jobDemand><commpanyName>北京多贝兄弟信息技术有限公司</commpanyName><commpanyDesc>不打卡 极客氛围 免费午餐 六险一金</commpanyDesc><posCount>10个职位</posCount></Job><Job><jobTitle>运维开发工程师</jobTitle><jobSaray>15-25K/月</jobSaray><jobDemand>北京市 本科 3-5年</jobDemand><commpanyName>北京多贝兄弟信息技术有限公司</commpanyName><commpanyDesc>不打卡 极客氛围 免费午餐 六险一金</commpanyDesc><posCount>10个职位</posCount></Job><Job><jobTitle>Node.js开发工程师</jobTitle><jobSaray>15-25K/月</jobSaray><jobDemand>北京市 本科 1-3年</jobDemand><commpanyName>北京多贝兄弟信息技术有限公司</commpanyName><commpanyDesc>不打卡 极客氛围 免费午餐 六险一金</commpanyDesc><posCount>10个职位</posCount></Job><Job><jobTitle>C++开发（客户端）</jobTitle><jobSaray>15-30K/月</jobSaray><jobDemand>北京市 本科 1-3年</jobDemand><commpanyName>北京多贝兄弟信息技术有限公司</commpanyName><commpanyDesc>不打卡 极客氛围 免费午餐 六险一金</commpanyDesc><posCount>10个职位</posCount></Job><Job><jobTitle>软件测试开发工程师</jobTitle><jobSaray>15-25K/月</jobSaray><jobDemand>北京市 本科 3-5年</jobDemand><commpanyName>北京多贝兄弟信息技术有限公司</commpanyName><commpanyDesc>不打卡 极客氛围 免费午餐 六险一金</commpanyDesc><posCount>10个职位</posCount></Job><Job><jobTitle>JAVA Engineer</jobTitle><jobSaray>15-25K/月</jobSaray><jobDemand>厦门市 本科 5-10年</jobDemand><commpanyName>厦门铃盛软件公司</commpanyName><commpanyDesc>内部员工持股 人文关怀 海景办公 六险一金 大牛同事</commpanyDesc><posCount>1个职位</posCount></Job><Job><jobTitle>算法工程师</jobTitle><jobSaray>18-22K/月</jobSaray><jobDemand>深圳市 硕士 应届生</jobDemand><commpanyName>睿初科技（深圳）有限公司</commpanyName><commpanyDesc>无</commpanyDesc><posCount>6个职位</posCount></Job><Job><jobTitle>数据挖掘工程师</jobTitle><jobSaray>18-30K/月</jobSaray><jobDemand>北京市 本科 3-5年</jobDemand><commpanyName>北京牛客科技有限公司</commpanyName><commpanyDesc>快速提升 扁平化 海外旅行 竞争性薪酬</commpanyDesc><posCount>3个职位</posCount></Job><Job><jobTitle>C++后台软件开发工程师</jobTitle><jobSaray>14-20K/月</jobSaray><jobDemand>深圳市 本科 1年以下</jobDemand><commpanyName>睿初科技（深圳）有限公司</commpanyName><commpanyDesc>无</commpanyDesc><posCount>6个职位</posCount></Job><Job><jobTitle>软件测试工程师</jobTitle><jobSaray>15-20K/月</jobSaray><jobDemand>深圳市 本科 1年以下</jobDemand><commpanyName>睿初科技（深圳）有限公司</commpanyName><commpanyDesc>无</commpanyDesc><posCount>6个职位</posCount></Job><Job><jobTitle>软件测试工程师</jobTitle><jobSaray>4-4K/月</jobSaray><jobDemand>深圳市 本科 应届生</jobDemand><commpanyName>睿初科技（深圳）有限公司</commpanyName><commpanyDesc>无</commpanyDesc><posCount>6个职位</posCount></Job><Job><jobTitle>软件测试工程师</jobTitle><jobSaray>10-15K/月</jobSaray><jobDemand>杭州市 本科 1-3年</jobDemand><commpanyName>杭州钛鑫科技有限公司</commpanyName><commpanyDesc>团康活动 年终奖金 年休 五险一金 双休</commpanyDesc><posCount>2个职位</posCount></Job><Job><jobTitle>高级java开发工程师</jobTitle><jobSaray>15-25K/月</jobSaray><jobDemand>杭州市 本科 3-5年</jobDemand><commpanyName>杭州钛鑫科技有限公司</commpanyName><commpanyDesc>年休假 年度旅游 团康活动 五险一金 餐补</commpanyDesc><posCount>2个职位</posCount></Job><Job><jobTitle>高级推荐算法工程师（T3-1~T3-3）</jobTitle><jobSaray>25-50K/月</jobSaray><jobDemand>广州市 本科 3-5年</jobDemand><commpanyName>广州宏熹人力资源服务有限公司</commpanyName><commpanyDesc>无</commpanyDesc><posCount>10个职位</posCount></Job><Job><jobTitle>高级后台开发工程师（大数据推荐算法方向）</jobTitle><jobSaray>25-50K/月</jobSaray><jobDemand>广州市 本科 1-3年</jobDemand><commpanyName>广州宏熹人力资源服务有限公司</commpanyName><commpanyDesc>无</commpanyDesc><posCount>10个职位</posCount></Job><Job><jobTitle>资深计算机视觉算法工程师（AI实验室）</jobTitle><jobSaray>30-60K/月</jobSaray><jobDemand>杭州市 硕士 3-5年</jobDemand><commpanyName>广州宏熹人力资源服务有限公司</commpanyName><commpanyDesc>无</commpanyDesc><posCount>10个职位</posCount></Job><Job><jobTitle>深度学习工程师（AI实验室）</jobTitle><jobSaray>30-60K/月</jobSaray><jobDemand>杭州市 本科 1-3年</jobDemand><commpanyName>广州宏熹人力资源服务有限公司</commpanyName><commpanyDesc>无</commpanyDesc><posCount>10个职位</posCount></Job><Job><jobTitle>自然语言处理（NLP）算法专家（可Lea...</jobTitle><jobSaray>50-100K/月</jobSaray><jobDemand>杭州市 硕士 3-5年</jobDemand><commpanyName>广州宏熹人力资源服务有限公司</commpanyName><commpanyDesc>无</commpanyDesc><posCount>10个职位</posCount></Job><Job><jobTitle></jobTitle><jobSaray>15-20K/月</jobSaray><jobDemand>上海市 本科 3-5年</jobDemand><commpanyName>南京美仕优杰企业管理咨询有限公司</commpanyName><commpanyDesc>平台发展 外企</commpanyDesc><posCount>5个职位</posCount></Job><Job><jobTitle>深度强化学习研究员（AI实验室）</jobTitle><jobSaray>50-100K/月</jobSaray><jobDemand>杭州市 硕士 1-3年</jobDemand><commpanyName>广州宏熹人力资源服务有限公司</commpanyName><commpanyDesc>无</commpanyDesc><posCount>10个职位</posCount></Job><Job><jobTitle>嵌入式软件工程师</jobTitle><jobSaray>4-8K/月</jobSaray><jobDemand>西安市 本科 1-3年</jobDemand><commpanyName>西安非凡士机器人科技有限公司</commpanyName><commpanyDesc>轻松办公氛围 创新团队 社保保险</commpanyDesc><posCount>1个职位</posCount></Job><Job><jobTitle>C++服务端</jobTitle><jobSaray>10-15K/月</jobSaray><jobDemand>南宁市 本科 3-5年</jobDemand><commpanyName>广西杰米网络科技有限公司</commpanyName><commpanyDesc>有阿姨做饭 周末双休</commpanyDesc><posCount>3个职位</posCount></Job><Job><jobTitle>游戏UI设计师</jobTitle><jobSaray>5-6K/月</jobSaray><jobDemand>南宁市 大专 1-3年</jobDemand><commpanyName>广西杰米网络科技有限公司</commpanyName><commpanyDesc>年终奖 周末双休 包午晚餐</commpanyDesc><posCount>3个职位</posCount></Job><Job><jobTitle>Android开发（高级）工程师 - 独...</jobTitle><jobSaray>20-40K/月</jobSaray><jobDemand>上海市 本科 3-5年</jobDemand><commpanyName>北京字节跳动网络技术有限公司</commpanyName><commpanyDesc>免费三餐 悠闲下午茶 租房补贴-带薪休假</commpanyDesc><posCount>26个职位</posCount></Job><Job><jobTitle>服务端(高级)工程师 - 独立闭环业务</jobTitle><jobSaray>20-40K/月</jobSaray><jobDemand>上海市 本科 3-5年</jobDemand><commpanyName>北京字节跳动网络技术有限公司</commpanyName><commpanyDesc>免费三餐 优秀团队 悠闲下午茶 租房补贴-带薪休假</commpanyDesc><posCount>26个职位</posCount></Job><Job><jobTitle>（资深）前端工程师</jobTitle><jobSaray>18-30K/月</jobSaray><jobDemand>上海市 本科 3-5年</jobDemand><commpanyName>携程旅行网</commpanyName><commpanyDesc>无</commpanyDesc><posCount>1个职位</posCount></Job><Job><jobTitle>区块链开发工程师</jobTitle><jobSaray>20-30K/月</jobSaray><jobDemand>深圳市 本科 3-5年</jobDemand><commpanyName>南京美仕优杰企业管理咨询有限公司&lt;/a&gt;  5个职位 2018-07-05更新 </commpanyName><commpanyDesc>一切靠实力 用人不拘一格 平台发展</commpanyDesc><posCount>5个职位</posCount></Job><Job><jobTitle>Web 前端工程师</jobTitle><jobSaray>15-30K/月</jobSaray><jobDemand>上海市 本科 3-5年</jobDemand><commpanyName>Web 前端工程师 我要应聘 收藏 上海恬胜信息科技有限公司</commpanyName><commpanyDesc>outing 年度体检 五险一金 工作餐 氛围好</commpanyDesc><posCount>3个职位</posCount></Job><Job><jobTitle>后端工程师 Node.js</jobTitle><jobSaray>15-30K/月</jobSaray><jobDemand>上海市 本科 3-5年</jobDemand><commpanyName>上海恬胜信息科技有限公司</commpanyName><commpanyDesc>outing 氛围好 工作餐 年度体检 五险一金</commpanyDesc><posCount>3个职位</posCount></Job><Job><jobTitle>Go开发工程师</jobTitle><jobSaray>15-30K/月</jobSaray><jobDemand>上海市 本科 3-5年</jobDemand><commpanyName>上海恬胜信息科技有限公司</commpanyName><commpanyDesc>outing 工作餐 年度体检 五险一金 氛围好</commpanyDesc><posCount>3个职位</posCount></Job><Job><jobTitle>Java架构师（支付，交易方向）</jobTitle><jobSaray>30-50K/月</jobSaray><jobDemand>深圳市 本科 5-10年</jobDemand><commpanyName>南京美仕优杰企业管理咨询有限公司</commpanyName><commpanyDesc>平台发展 用人不拘一格</commpanyDesc><posCount>5个职位</posCount></Job><Job><jobTitle>java高级工程师（后端）</jobTitle><jobSaray>20-40K/月</jobSaray><jobDemand>北京市 本科 5-10年</jobDemand><commpanyName>上海沃锐企业发展有限公司</commpanyName><commpanyDesc>双休 五险一金-公司福利</commpanyDesc><posCount>2个职位</posCount></Job><Job><jobTitle>web服务器端工程师</jobTitle><jobSaray>10-20K/月</jobSaray><jobDemand>上海市 本科 1-3年</jobDemand><commpanyName>职优你（上海）教育科技有限公司</commpanyName><commpanyDesc>无</commpanyDesc><posCount>5个职位</posCount></Job><Job><jobTitle>web前端工程师</jobTitle><jobSaray>10-20K/月</jobSaray><jobDemand>上海市 本科 1-3年</jobDemand><commpanyName>职优你（上海）教育科技有限公司</commpanyName><commpanyDesc>技术大牛-朝阳行业</commpanyDesc><posCount>5个职位</posCount></Job><Job><jobTitle>中级/高级web前端工程师</jobTitle><jobSaray>15-25K/月</jobSaray><jobDemand>上海市 本科 3-5年</jobDemand><commpanyName>职优你（上海）教育科技有限公司</commpanyName><commpanyDesc>绩效奖金 临近地铁 团队nice 技术大牛-朝阳行业 成长空间大-环境氛围</commpanyDesc><posCount>5个职位</posCount></Job><Job><jobTitle>测试工程师</jobTitle><jobSaray>7-14K/月</jobSaray><jobDemand>上海市 本科 1-3年</jobDemand><commpanyName>职优你（上海）教育科技有限公司</commpanyName><commpanyDesc>成长空间大-环境氛围 绩效奖金 技术大牛-朝阳行业 临近地铁 团队nice</commpanyDesc><posCount>5个职位</posCount></Job><Job><jobTitle>高级Node.js开发工程师</jobTitle><jobSaray>20-30K/月</jobSaray><jobDemand>上海市 本科 3-5年</jobDemand><commpanyName>职优你（上海）教育科技有限公司</commpanyName><commpanyDesc>无</commpanyDesc><posCount>5个职位</posCount></Job><Job><jobTitle>Java开发工程师（高级）</jobTitle><jobSaray>19-30K/月</jobSaray><jobDemand>南京市 本科 5-10年</jobDemand><commpanyName>南京领添信息技术有限公司</commpanyName><commpanyDesc>五险一金-双休-大牛</commpanyDesc><posCount>6个职位</posCount></Job><Job><jobTitle>Cocos2d-lua/js开发工程师</jobTitle><jobSaray>8-15K/月</jobSaray><jobDemand>南宁市 大专 3-5年</jobDemand><commpanyName>广西杰米网络科技有限公司</commpanyName><commpanyDesc>带薪年假</commpanyDesc><posCount>3个职位</posCount></Job><Job><jobTitle>高级前端开发工程师/资深/专家</jobTitle><jobSaray>25-50K/月</jobSaray><jobDemand>杭州市 本科 3-5年</jobDemand><commpanyName>阿里巴巴集团</commpanyName><commpanyDesc>优秀人才阿里股票 有竞争力的薪酬 尊重个人发展意愿</commpanyDesc><posCount>52个职位</posCount></Job><Job><jobTitle>Android开发工程师</jobTitle><jobSaray>15-20K/月</jobSaray><jobDemand>杭州市 本科 1-3年</jobDemand><commpanyName>浙江孚临科技有限公司</commpanyName><commpanyDesc>无</commpanyDesc><posCount>9个职位</posCount></Job><Job><jobTitle>iOS开发工程师</jobTitle><jobSaray>15-20K/月</jobSaray><jobDemand>杭州市 本科 1-3年</jobDemand><commpanyName>浙江孚临科技有限公司</commpanyName><commpanyDesc>无</commpanyDesc><posCount>9个职位</posCount></Job><Job><jobTitle>前端开发工程师</jobTitle><jobSaray>18-25K/月</jobSaray><jobDemand>杭州市 本科 3-5年</jobDemand><commpanyName>浙江孚临科技有限公司</commpanyName><commpanyDesc>无</commpanyDesc><posCount>9个职位</posCount></Job><Job><jobTitle>高级java开发工程师（业务系统）</jobTitle><jobSaray>18-25K/月</jobSaray><jobDemand>杭州市 本科 3-5年</jobDemand><commpanyName>浙江孚临科技有限公司</commpanyName><commpanyDesc>无</commpanyDesc><posCount>9个职位</posCount></Job><Job><jobTitle>高级java开发工程师（平台）</jobTitle><jobSaray>18-25K/月</jobSaray><jobDemand>杭州市 本科 3-5年</jobDemand><commpanyName>浙江孚临科技有限公司</commpanyName><commpanyDesc>无</commpanyDesc><posCount>9个职位</posCount></Job><Job><jobTitle>Java架构师</jobTitle><jobSaray>30-35K/月</jobSaray><jobDemand>杭州市 本科 5-10年</jobDemand><commpanyName>浙江孚临科技有限公司</commpanyName><commpanyDesc>无</commpanyDesc><posCount>9个职位</posCount></Job><Job><jobTitle>数据仓库开发工程师</jobTitle><jobSaray>20-25K/月</jobSaray><jobDemand>杭州市 本科 3-5年</jobDemand><commpanyName>浙江孚临科技有限公司</commpanyName><commpanyDesc>无</commpanyDesc><posCount>9个职位</posCount></Job><Job><jobTitle>高级数据分析BI工程师</jobTitle><jobSaray>15-20K/月</jobSaray><jobDemand>杭州市 本科 3-5年</jobDemand><commpanyName>浙江孚临科技有限公司</commpanyName><commpanyDesc>无</commpanyDesc><posCount>9个职位</posCount></Job><Job><jobTitle>高级大数据平台开发工程师</jobTitle><jobSaray>20-28K/月</jobSaray><jobDemand>杭州市 本科 3-5年</jobDemand><commpanyName>浙江孚临科技有限公司</commpanyName><commpanyDesc>无</commpanyDesc><posCount>9个职位</posCount></Job><Job><jobTitle>Java开发（工具组）</jobTitle><jobSaray>18-36K/月</jobSaray><jobDemand>杭州市 本科 3-5年</jobDemand><commpanyName>点我达</commpanyName><commpanyDesc>成长空间大 团队氛围好 技术大牛 15-18薪 弹性工作制</commpanyDesc><posCount>8个职位</posCount></Job><Job><jobTitle>Web前端</jobTitle><jobSaray>15-30K/月</jobSaray><jobDemand>杭州市 本科 1-3年</jobDemand><commpanyName>点我达</commpanyName><commpanyDesc>技术大牛 独角兽公司 成长空间大 团队氛围好</commpanyDesc><posCount>8个职位</posCount></Job><Job><jobTitle>应用运维工程师</jobTitle><jobSaray>10-20K/月</jobSaray><jobDemand>杭州市 本科 1-3年</jobDemand><commpanyName>点我达</commpanyName><commpanyDesc>成长空间大 弹性工作制 独角兽公司 技术大牛 团队氛围好</commpanyDesc><posCount>8个职位</posCount></Job><Job><jobTitle>中高级测试工程师</jobTitle><jobSaray>12-18K/月</jobSaray><jobDemand>杭州市 本科 3-5年</jobDemand><commpanyName>点我达</commpanyName><commpanyDesc>技术大牛 成长空间大 弹性工作制 独角兽公司 团队氛围好</commpanyDesc><posCount>8个职位</posCount></Job><Job><jobTitle>淘宝-新制造 前端专家</jobTitle><jobSaray>15-30K/月</jobSaray><jobDemand>杭州市 本科 3-5年</jobDemand><commpanyName>阿里巴巴集团</commpanyName><commpanyDesc>尊重个人发展意愿 有竞争力的薪酬 优秀人才阿里股票</commpanyDesc><posCount>52个职位</posCount></Job><Job><jobTitle>淘宝-新制造 前端开发工程师</jobTitle><jobSaray>15-30K/月</jobSaray><jobDemand>杭州市 本科 3-5年</jobDemand><commpanyName>阿里巴巴集团</commpanyName><commpanyDesc>有竞争力的薪酬 优秀人才阿里股票 尊重个人发展意愿</commpanyDesc><posCount>52个职位</posCount></Job><Job><jobTitle>淘宝-新制造 高级测试开发工程师</jobTitle><jobSaray>18-36K/月</jobSaray><jobDemand>杭州市 本科 3-5年</jobDemand><commpanyName>阿里巴巴集团</commpanyName><commpanyDesc>有竞争力的薪酬 优秀人才阿里股票 尊重个人发展意愿</commpanyDesc><posCount>52个职位</posCount></Job><Job><jobTitle>高级运维工程师</jobTitle><jobSaray>15-20K/月</jobSaray><jobDemand>广州市 本科 3-5年</jobDemand><commpanyName>广州冰鸟网络科技有限公司</commpanyName><commpanyDesc>50元-天餐补 福利活动多多 绩效奖金 年底双薪 五险一金</commpanyDesc><posCount>4个职位</posCount></Job><Job><jobTitle>PHP开发工程师</jobTitle><jobSaray>10-15K/月</jobSaray><jobDemand>广州市 本科 3-5年</jobDemand><commpanyName>广州冰鸟网络科技有限公司</commpanyName><commpanyDesc>50元-天餐补 福利活动多多 绩效奖金 年底双薪 五险一金</commpanyDesc><posCount>4个职位</posCount></Job><Job><jobTitle>Android高级开发工程师</jobTitle><jobSaray>15-25K/月</jobSaray><jobDemand>杭州市 本科 5-10年</jobDemand><commpanyName>华为技术有限公司</commpanyName><commpanyDesc>待遇优厚 挑战 战略方向</commpanyDesc><posCount>12个职位</posCount></Job><Job><jobTitle>质量顾问</jobTitle><jobSaray>8-12K/月</jobSaray><jobDemand>重庆市 本科 3-5年</jobDemand><commpanyName>上海外服（重庆）人力资源服务有限公司</commpanyName><commpanyDesc>福利优厚 公司潜力 晋升空间 行业发展好</commpanyDesc><posCount>3个职位</posCount></Job><Job><jobTitle>项目经理</jobTitle><jobSaray>10-15K/月</jobSaray><jobDemand>重庆市 本科 3-5年</jobDemand><commpanyName>上海外服（重庆）人力资源服务有限公司</commpanyName><commpanyDesc>福利优厚 公司潜力 晋升空间 行业发展好</commpanyDesc><posCount>3个职位</posCount></Job><Job><jobTitle>前端开发工程师（含实习）</jobTitle><jobSaray>15-30K/月</jobSaray><jobDemand>北京市 本科 1-3年</jobDemand><commpanyName>北京牛客科技有限公司</commpanyName><commpanyDesc>快速提升 扁平化 海外旅行 竞争性薪酬</commpanyDesc><posCount>3个职位</posCount></Job><Job><jobTitle>项目工程师</jobTitle><jobSaray>6-10K/月</jobSaray><jobDemand>重庆市 本科 1-3年</jobDemand><commpanyName>上海外服（重庆）人力资源服务有限公司</commpanyName><commpanyDesc>福利优厚 晋升空间 公司潜力 行业发展好</commpanyDesc><posCount>3个职位</posCount></Job><Job><jobTitle>JAVA开发工程师（含实习）</jobTitle><jobSaray>15-30K/月</jobSaray><jobDemand>北京市 本科 1-3年</jobDemand><commpanyName>北京牛客科技有限公司</commpanyName><commpanyDesc>快速提升 扁平化 海外旅行 竞争性薪酬</commpanyDesc><posCount>3个职位</posCount></Job><Job><jobTitle>图像处理算法工程师</jobTitle><jobSaray>40-80K/月</jobSaray><jobDemand>广州市 本科 1-3年</jobDemand><commpanyName>广州宏熹人力资源服务有限公司</commpanyName><commpanyDesc>极具吸引力的薪酬</commpanyDesc><posCount>10个职位</posCount></Job><Job><jobTitle></jobTitle><jobSaray>15-20K/月</jobSaray><jobDemand>深圳市 本科 1-3年</jobDemand><commpanyName>睿初科技（深圳）有限公司</commpanyName><commpanyDesc>无</commpanyDesc><posCount>6个职位</posCount></Job><Job><jobTitle>音频算法高级工程师</jobTitle><jobSaray>60-120K/月</jobSaray><jobDemand>广州市 本科 3-5年</jobDemand><commpanyName>广州宏熹人力资源服务有限公司</commpanyName><commpanyDesc>互联网行业上市公司</commpanyDesc><posCount>10个职位</posCount></Job><Job><jobTitle>C++工程师</jobTitle><jobSaray>15-25K/月</jobSaray><jobDemand>上海市 本科 1-3年</jobDemand><commpanyName>上海沃锐企业发展有限公司</commpanyName><commpanyDesc>双休 五险一金-公司福利</commpanyDesc><posCount>2个职位</posCount></Job><Job><jobTitle>机器学习算法工程师</jobTitle><jobSaray>60-120K/月</jobSaray><jobDemand>广州市 硕士 1-3年</jobDemand><commpanyName>广州宏熹人力资源服务有限公司</commpanyName><commpanyDesc>互联网上市公司</commpanyDesc><posCount>10个职位</posCount></Job><Job><jobTitle>PHP工程师</jobTitle><jobSaray>6-9K/月</jobSaray><jobDemand>武汉市 本科 1-3年</jobDemand><commpanyName>阿哈王国（武汉）教育科技有限公司</commpanyName><commpanyDesc>大牛团队 五险一金 项目前景好</commpanyDesc><posCount>4个职位</posCount></Job><Job><jobTitle>计算机视觉算法工程师</jobTitle><jobSaray>50-100K/月</jobSaray><jobDemand>广州市 硕士 3-5年</jobDemand><commpanyName>广州宏熹人力资源服务有限公司</commpanyName><commpanyDesc>互联网行业上市公司</commpanyDesc><posCount>10个职位</posCount></Job><Job><jobTitle>前端开发工程师</jobTitle><jobSaray>6-12K/月</jobSaray><jobDemand>武汉市 本科 1-3年</jobDemand><commpanyName>阿哈王国（武汉）教育科技有限公司</commpanyName><commpanyDesc>大牛团队 五险一金 项目前景好</commpanyDesc><posCount>4个职位</posCount></Job><Job><jobTitle>高级UI</jobTitle><jobSaray>8-15K/月</jobSaray><jobDemand>成都市 大专 3-5年</jobDemand><commpanyName>成都市晓易互动科技有限公司</commpanyName><commpanyDesc>全勤奖 不定期旅游 社保公积金 定期体检 周末双休</commpanyDesc><posCount>9个职位</posCount></Job><Job><jobTitle>全栈开发工程师</jobTitle><jobSaray>15-20K/月</jobSaray><jobDemand>武汉市 本科 3-5年</jobDemand><commpanyName>阿哈王国（武汉）教育科技有限公司</commpanyName><commpanyDesc>大牛团队 五险一金 项目前景好</commpanyDesc><posCount>4个职位</posCount></Job><Job><jobTitle>2D主美</jobTitle><jobSaray>10-15K/月</jobSaray><jobDemand>成都市 大专 5-10年</jobDemand><commpanyName>成都市晓易互动科技有限公司</commpanyName><commpanyDesc>定期体检 不定期旅游 全勤奖 社保公积金 周末双休</commpanyDesc><posCount>9个职位</posCount></Job><Job><jobTitle>Cocos2d-js高级游戏开发工程师</jobTitle><jobSaray></jobSaray><jobDemand>武汉市 本科 1-3年</jobDemand><commpanyName>阿哈王国（武汉）教育科技有限公司</commpanyName><commpanyDesc>大牛团队 五险一金 项目前景好</commpanyDesc><posCount>4个职位</posCount></Job><Job><jobTitle>C++ 服务器开发工程师</jobTitle><jobSaray>15-30K/月</jobSaray><jobDemand>上海市 本科 3-5年</jobDemand><commpanyName>孤岛（上海）软件有限公司</commpanyName><commpanyDesc>住宿补贴 交通补贴 餐饮补贴 股票期权 五险一金</commpanyDesc><posCount>10个职位</posCount></Job><Job><jobTitle>U3D开发工程师</jobTitle><jobSaray>20-35K/月</jobSaray><jobDemand>上海市 本科 3-5年</jobDemand><commpanyName>孤岛（上海）软件有限公司</commpanyName><commpanyDesc>餐饮补贴 股票期权 交通补贴 五险一金 住宿补贴</commpanyDesc><posCount>10个职位</posCount></Job><Job><jobTitle>Cocos2d-x开发工程师</jobTitle><jobSaray>20-35K/月</jobSaray><jobDemand>上海市 本科 3-5年</jobDemand><commpanyName>孤岛（上海）软件有限公司</commpanyName><commpanyDesc>餐饮补贴 股票期权 交通补贴 五险一金 住宿补贴</commpanyDesc><posCount>10个职位</posCount></Job><Job><jobTitle>Golang开发工程师</jobTitle><jobSaray>15-30K/月</jobSaray><jobDemand>上海市 本科 3-5年</jobDemand><commpanyName>孤岛（上海）软件有限公司</commpanyName><commpanyDesc>餐饮补贴 股票期权 交通补贴 五险一金 住宿补贴</commpanyDesc><posCount>10个职位</posCount></Job><Job><jobTitle>Java服务器开发工程师</jobTitle><jobSaray>20-35K/月</jobSaray><jobDemand>上海市 本科 3-5年</jobDemand><commpanyName>孤岛（上海）软件有限公司</commpanyName><commpanyDesc>餐饮补贴 股票期权 交通补贴 五险一金 住宿补贴</commpanyDesc><posCount>10个职位</posCount></Job><Job><jobTitle>Node.js开发工程师</jobTitle><jobSaray>15-30K/月</jobSaray><jobDemand>上海市 本科 3-5年</jobDemand><commpanyName>孤岛（上海）软件有限公司</commpanyName><commpanyDesc>餐饮补贴 股票期权 交通补贴 五险一金 住宿补贴</commpanyDesc><posCount>10个职位</posCount></Job><Job><jobTitle>Android SDK开发</jobTitle><jobSaray>15-30K/月</jobSaray><jobDemand>上海市 本科 3-5年</jobDemand><commpanyName>孤岛（上海）软件有限公司</commpanyName><commpanyDesc>餐饮补贴 股票期权 交通补贴 五险一金 住宿补贴</commpanyDesc><posCount>10个职位</posCount></Job><Job><jobTitle>算法研究员</jobTitle><jobSaray>30-50K/月</jobSaray><jobDemand>杭州市 硕士 1-3年</jobDemand><commpanyName>点我达</commpanyName><commpanyDesc>成长空间大 弹性工作制 独角兽公司 团队氛围好</commpanyDesc><posCount>8个职位</posCount></Job><Job><jobTitle>DBA工程师/专家</jobTitle><jobSaray>15-30K/月</jobSaray><jobDemand>杭州市 本科 3-5年</jobDemand><commpanyName>点我达</commpanyName><commpanyDesc>无</commpanyDesc><posCount>8个职位</posCount></Job><Job><jobTitle>Java开发工程师（调度方向）</jobTitle><jobSaray>15-30K/月</jobSaray><jobDemand>杭州市 本科 3-5年</jobDemand><commpanyName>点我达</commpanyName><commpanyDesc>成长空间大 弹性工作制 独角兽公司 技术大牛 团队氛围好</commpanyDesc><posCount>8个职位</posCount></Job><Job><jobTitle>Android开发工程师</jobTitle><jobSaray>15-30K/月</jobSaray><jobDemand>杭州市 本科 3-5年</jobDemand><commpanyName>点我达</commpanyName><commpanyDesc>成长空间大 弹性工作制 独角兽公司 技术大牛 团队氛围好</commpanyDesc><posCount>8个职位</posCount></Job><Job><jobTitle>运维工程师</jobTitle><jobSaray>12-24K/月</jobSaray><jobDemand>北京市 本科 3-5年</jobDemand><commpanyName>北京创金启富基金销售有限公司</commpanyName><commpanyDesc>加班餐补 带薪年假 股票期权 节日福利</commpanyDesc><posCount>2个职位</posCount></Job><Job><jobTitle>资深JAVA工程师</jobTitle><jobSaray>15-30K/月</jobSaray><jobDemand>北京市 本科 3-5年</jobDemand><commpanyName>北京创金启富基金销售有限公司</commpanyName><commpanyDesc>带薪年假 节日福利 股票期权</commpanyDesc><posCount>2个职位</posCount></Job><Job><jobTitle>技术美术</jobTitle><jobSaray>13-25K/月</jobSaray><jobDemand>北京市 本科 3-5年</jobDemand><commpanyName>苏州美房云客软件科技股份有限公司</commpanyName><commpanyDesc>年终奖 节日福利多多 五险一金</commpanyDesc><posCount>2个职位</posCount></Job><Job><jobTitle>UE4</jobTitle><jobSaray>8-15K/月</jobSaray><jobDemand>北京市 本科 1-3年</jobDemand><commpanyName>苏州美房云客软件科技股份有限公司</commpanyName><commpanyDesc>年终奖 五险一金 专人培训 发展空间大 上市公司</commpanyDesc><posCount>2个职位</posCount></Job><Job><jobTitle>web工程师</jobTitle><jobSaray>13-16K/月</jobSaray><jobDemand>深圳市 大专 3-5年</jobDemand><commpanyName>北京新致方舟科技有限公司</commpanyName><commpanyDesc>java vue</commpanyDesc><posCount>1个职位</posCount></Job><Job><jobTitle>系统安全工程师</jobTitle><jobSaray>25-50K/月</jobSaray><jobDemand>北京市 本科 3-5年</jobDemand><commpanyName>北京仕邦达人力资源有限公司</commpanyName><commpanyDesc>TOP互联网公司 核心部门核心业务 16薪</commpanyDesc><posCount>16个职位</posCount></Job><Job><jobTitle>测试开发工程师</jobTitle><jobSaray>25-50K/月</jobSaray><jobDemand>北京市 本科 3-5年</jobDemand><commpanyName>北京仕邦达人力资源有限公司</commpanyName><commpanyDesc>核心部门核心业务 TOP互联网公司 16薪</commpanyDesc><posCount>16个职位</posCount></Job><Job><jobTitle>高级推荐引擎开发工程师</jobTitle><jobSaray>25-50K/月</jobSaray><jobDemand>北京市 本科 5-10年</jobDemand><commpanyName>北京仕邦达人力资源有限公司</commpanyName><commpanyDesc>TOP互联网公司 核心部门核心业务 16薪</commpanyDesc><posCount>16个职位</posCount></Job><Job><jobTitle>高级架构研发工程师 （地图事业部）</jobTitle><jobSaray>25-50K/月</jobSaray><jobDemand>北京市 本科 5-10年</jobDemand><commpanyName>北京仕邦达人力资源有限公司</commpanyName><commpanyDesc>16薪 核心部门核心业务 TOP互联网公司</commpanyDesc><posCount>16个职位</posCount></Job><Job><jobTitle>高级策略算法工程师</jobTitle><jobSaray>30-50K/月</jobSaray><jobDemand>北京市 本科 5-10年</jobDemand><commpanyName>北京仕邦达人力资源有限公司</commpanyName><commpanyDesc>TOP互联网公司 核心部门核心业务 16薪</commpanyDesc><posCount>16个职位</posCount></Job><Job><jobTitle>Java架构师</jobTitle><jobSaray>15-30K/月</jobSaray><jobDemand>深圳市 本科 3-5年</jobDemand><commpanyName>深圳市海恒图联软件有限公司</commpanyName><commpanyDesc>无</commpanyDesc><posCount>1个职位</posCount></Job><Job><jobTitle>GUI开发工程师</jobTitle><jobSaray>12-24K/月</jobSaray><jobDemand>深圳市 本科 1-3年</jobDemand><commpanyName>东方晶源微电子科技（北京）有限公司深圳分公司</commpanyName><commpanyDesc>无</commpanyDesc><posCount>2个职位</posCount></Job><Job><jobTitle>C++资深工程师（30-60k/月）</jobTitle><jobSaray>30-60K/月</jobSaray><jobDemand>北京市 本科 3-5年</jobDemand><commpanyName>北京善思为科技有限公司</commpanyName><commpanyDesc>无</commpanyDesc><posCount>2个职位</posCount></Job><Job><jobTitle>算法工程师</jobTitle><jobSaray>13-25K/月</jobSaray><jobDemand>深圳市 硕士 1-3年</jobDemand><commpanyName>东方晶源微电子科技（北京）有限公司深圳分公司</commpanyName><commpanyDesc>无</commpanyDesc><posCount>2个职位</posCount></Job><Job><jobTitle>ERP软件工程师</jobTitle><jobSaray>12-20K/月</jobSaray><jobDemand>北京市 本科 1-3年</jobDemand><commpanyName>中国中纺集团</commpanyName><commpanyDesc>SAP和ORACLE 培训机会</commpanyDesc><posCount>1个职位</posCount></Job><Job><jobTitle>高级Java工程师（30-50k/月）</jobTitle><jobSaray>30-50K/月</jobSaray><jobDemand>北京市 本科 3-5年</jobDemand><commpanyName>北京善思为科技有限公司</commpanyName><commpanyDesc>无</commpanyDesc><posCount>2个职位</posCount></Job><Job><jobTitle>C#软件工程师</jobTitle><jobSaray>10-20K/月</jobSaray><jobDemand>上海市 本科 3-5年</jobDemand><commpanyName>上海爱圣美科技有限公司</commpanyName><commpanyDesc>无</commpanyDesc><posCount>1个职位</posCount></Job><Job><jobTitle>阿里影业-产品技术-前端开发/专家</jobTitle><jobSaray>30-55K/月</jobSaray><jobDemand>广州市 本科 3-5年</jobDemand><commpanyName>广东阿里影业云智软件有限公司</commpanyName><commpanyDesc>无</commpanyDesc><posCount>1个职位</posCount></Job><Job><jobTitle>高级java工程师</jobTitle><jobSaray>20-30K/月</jobSaray><jobDemand>北京市 本科 5-10年</jobDemand><commpanyName>云像（上海）数字技术有限公司</commpanyName><commpanyDesc>无</commpanyDesc><posCount>3个职位</posCount></Job><Job><jobTitle>测试开发工程师</jobTitle><jobSaray>10-20K/月</jobSaray><jobDemand>北京市 本科 3-5年</jobDemand><commpanyName>云像（上海）数字技术有限公司</commpanyName><commpanyDesc>无</commpanyDesc><posCount>3个职位</posCount></Job><Job><jobTitle>前端工程师</jobTitle><jobSaray>15-30K/月</jobSaray><jobDemand>北京市 本科 3-5年</jobDemand><commpanyName>云像（上海）数字技术有限公司</commpanyName><commpanyDesc>无</commpanyDesc><posCount>3个职位</posCount></Job><Job><jobTitle>QT软件开发工程师</jobTitle><jobSaray>6-10K/月</jobSaray><jobDemand>长沙市 大专 3-5年</jobDemand><commpanyName>长沙千视电子科技有限公司</commpanyName><commpanyDesc>无</commpanyDesc><posCount>10个职位</posCount></Job><Job><jobTitle>嵌入式linux多媒体应用开发工程师</jobTitle><jobSaray>8-12K/月</jobSaray><jobDemand>长沙市 本科 1-3年</jobDemand><commpanyName>长沙千视电子科技有限公司</commpanyName><commpanyDesc>无</commpanyDesc><posCount>10个职位</posCount></Job><Job><jobTitle>web全栈工程师</jobTitle><jobSaray>10-16K/月</jobSaray><jobDemand>长沙市 大专 1-3年</jobDemand><commpanyName>长沙千视电子科技有限公司</commpanyName><commpanyDesc>无</commpanyDesc><posCount>10个职位</posCount></Job><Job><jobTitle>FPGA图像处理开发工程师</jobTitle><jobSaray>10-16K/月</jobSaray><jobDemand>长沙市 本科 3-5年</jobDemand><commpanyName>长沙千视电子科技有限公司</commpanyName><commpanyDesc>无</commpanyDesc><posCount>10个职位</posCount></Job><Job><jobTitle>嵌入式Linux底层开发工程师</jobTitle><jobSaray>10-15K/月</jobSaray><jobDemand>长沙市 本科 3-5年</jobDemand><commpanyName>长沙千视电子科技有限公司</commpanyName><commpanyDesc>无</commpanyDesc><posCount>10个职位</posCount></Job><Job><jobTitle>C#总监</jobTitle><jobSaray>20-40K/月</jobSaray><jobDemand>深圳市 本科 5-10年</jobDemand><commpanyName>深圳市小号科技有限公司</commpanyName><commpanyDesc>无</commpanyDesc><posCount>3个职位</posCount></Job><Job><jobTitle>.Net 爬虫工程师</jobTitle><jobSaray>12-24K/月</jobSaray><jobDemand>深圳市 大专 1-3年</jobDemand><commpanyName>深圳市小号科技有限公司</commpanyName><commpanyDesc>无</commpanyDesc><posCount>3个职位</posCount></Job><Job><jobTitle>Asp.NET CORE 开发工程师</jobTitle><jobSaray>12-24K/月</jobSaray><jobDemand>深圳市 大专 1-3年</jobDemand><commpanyName>深圳市小号科技有限公司</commpanyName><commpanyDesc>无</commpanyDesc><posCount>3个职位</posCount></Job><Job><jobTitle>高级java开发工程师</jobTitle><jobSaray>10-20K/月</jobSaray><jobDemand>武汉市 本科 3-5年</jobDemand><commpanyName>武汉烧麦财播科技有限公司</commpanyName><commpanyDesc>福利多-空间大</commpanyDesc><posCount>2个职位</posCount></Job><Job><jobTitle>java高级工程师</jobTitle><jobSaray>10-20K/月</jobSaray><jobDemand>武汉市 本科 3-5年</jobDemand><commpanyName>武汉烧麦财播科技有限公司</commpanyName><commpanyDesc>福利多-空间大</commpanyDesc><posCount>2个职位</posCount></Job><Job><jobTitle>DBA</jobTitle><jobSaray>10-18K/月</jobSaray><jobDemand>广州市 本科 3-5年</jobDemand><commpanyName>广州广电运通信息科技有限公司</commpanyName><commpanyDesc>福利好 双休 年终奖 绩效奖金 六险一金</commpanyDesc><posCount>2个职位</posCount></Job><Job><jobTitle>系统架构师</jobTitle><jobSaray>20-30K/月</jobSaray><jobDemand>广州市 本科 5-10年</jobDemand><commpanyName>广州广电运通信息科技有限公司</commpanyName><commpanyDesc>福利好 双休 绩效奖金 年终奖 六险一金</commpanyDesc><posCount>2个职位</posCount></Job><Job><jobTitle>前端软件开发工程师</jobTitle><jobSaray>20-30K/月</jobSaray><jobDemand>深圳市 本科 3-5年</jobDemand><commpanyName>华润深国投信托有限公司</commpanyName><commpanyDesc>无</commpanyDesc><posCount>1个职位</posCount></Job><Job><jobTitle>Java工程师</jobTitle><jobSaray>10-15K/月</jobSaray><jobDemand>西安市 本科 3-5年</jobDemand><commpanyName>陕西深度网络有限公司</commpanyName><commpanyDesc>节日福利 双休 小零食</commpanyDesc><posCount>1个职位</posCount></Job><Job><jobTitle>知名大厂-资深前端工程师</jobTitle><jobSaray>20-40K/月</jobSaray><jobDemand>杭州市 本科 3-5年</jobDemand><commpanyName>第一资本猎头</commpanyName><commpanyDesc>前景一片光明 奖金丰厚 RSU 股票 期权</commpanyDesc><posCount>1个职位</posCount></Job><Job><jobTitle>IOS研发工程师</jobTitle><jobSaray>6-8K/月</jobSaray><jobDemand>成都市 大专 1-3年</jobDemand><commpanyName>深圳市凌盟科技有限公司</commpanyName><commpanyDesc>带薪休假 下午茶 绩效奖金 岗位分红 五险一金</commpanyDesc><posCount>2个职位</posCount></Job><Job><jobTitle>测试软件工程师</jobTitle><jobSaray>10-15K/月</jobSaray><jobDemand>杭州市 本科 3-5年</jobDemand><commpanyName>浙江互灵物联科技有限公司</commpanyName><commpanyDesc>无</commpanyDesc><posCount>5个职位</posCount></Job><Job><jobTitle>产品经理</jobTitle><jobSaray>10-15K/月</jobSaray><jobDemand>杭州市 本科 3-5年</jobDemand><commpanyName>浙江互灵物联科技有限公司</commpanyName><commpanyDesc>无</commpanyDesc><posCount>5个职位</posCount></Job><Job><jobTitle>web前端工程师</jobTitle><jobSaray>10-15K/月</jobSaray><jobDemand>杭州市 本科 3-5年</jobDemand><commpanyName>浙江互灵物联科技有限公司</commpanyName><commpanyDesc>无</commpanyDesc><posCount>5个职位</posCount></Job><Job><jobTitle>JAVA后端开发工程师</jobTitle><jobSaray>10-15K/月</jobSaray><jobDemand>杭州市 大专 3-5年</jobDemand><commpanyName>浙江互灵物联科技有限公司</commpanyName><commpanyDesc>无</commpanyDesc><posCount>5个职位</posCount></Job><Job><jobTitle>Web后端开发工程师</jobTitle><jobSaray>7-10K/月</jobSaray><jobDemand>长沙市 本科 1-3年</jobDemand><commpanyName>长沙千视电子科技有限公司</commpanyName><commpanyDesc>无</commpanyDesc><posCount>10个职位</posCount></Job><Job><jobTitle>Python/Lua软件开发工程师</jobTitle><jobSaray>6-10K/月</jobSaray><jobDemand>长沙市 大专 1-3年</jobDemand><commpanyName>长沙千视电子科技有限公司</commpanyName><commpanyDesc>无</commpanyDesc><posCount>10个职位</posCount></Job><Job><jobTitle>Android/iOS多媒体应用开发工程...</jobTitle><jobSaray>8-12K/月</jobSaray><jobDemand>长沙市 大专 1-3年</jobDemand><commpanyName>长沙千视电子科技有限公司</commpanyName><commpanyDesc>无</commpanyDesc><posCount>10个职位</posCount></Job><Job><jobTitle>(C/C++)流媒体协议应用开发工程师</jobTitle><jobSaray>8-12K/月</jobSaray><jobDemand>长沙市 本科 1-3年</jobDemand><commpanyName>长沙千视电子科技有限公司</commpanyName><commpanyDesc>无</commpanyDesc><posCount>10个职位</posCount></Job><Job><jobTitle>Web前端开发工程师</jobTitle><jobSaray>5-8K/月</jobSaray><jobDemand>长沙市 大专 1-3年</jobDemand><commpanyName>长沙千视电子科技有限公司</commpanyName><commpanyDesc>无</commpanyDesc><posCount>10个职位</posCount></Job><Job><jobTitle>Java高级工程师</jobTitle><jobSaray>7-10K/月</jobSaray><jobDemand>济南市 本科 3-5年</jobDemand><commpanyName>上海易贸商务发展有限公司</commpanyName><commpanyDesc>商城 ssm ssh Java</commpanyDesc><posCount>3个职位</posCount></Job><Job><jobTitle>软件测试工程师</jobTitle><jobSaray>6-9K/月</jobSaray><jobDemand>济南市 本科 1-3年</jobDemand><commpanyName>上海易贸商务发展有限公司</commpanyName><commpanyDesc>功能测试 白盒测试 黑盒测试 自动化测试 性能测试</commpanyDesc><posCount>3个职位</posCount></Job><Job><jobTitle>web前端开发工程师</jobTitle><jobSaray>6-10K/月</jobSaray><jobDemand>济南市 本科 1-3年</jobDemand><commpanyName>上海易贸商务发展有限公司</commpanyName><commpanyDesc>互联网风口项目 微信小程序 web前端 vue</commpanyDesc><posCount>3个职位</posCount></Job><Job><jobTitle>.net开发工程师</jobTitle><jobSaray>7-13K/月</jobSaray><jobDemand>深圳市 本科 1-3年</jobDemand><commpanyName>深圳市利国投资有限公司</commpanyName><commpanyDesc>股票期权 发展前景广 办公环境好 不定期涨薪</commpanyDesc><posCount>1个职位</posCount></Job><Job><jobTitle>前端开发工程师</jobTitle><jobSaray>25-50K/月</jobSaray><jobDemand>北京市 本科 3-5年</jobDemand><commpanyName>北京仕邦达人力资源有限公司</commpanyName><commpanyDesc>TOP互联网公司 核心部门核心业务 16薪</commpanyDesc><posCount>16个职位</posCount></Job><Job><jobTitle>PHP高级工程师</jobTitle><jobSaray>20-40K/月</jobSaray><jobDemand>北京市 本科 3-5年</jobDemand><commpanyName>北京仕邦达人力资源有限公司</commpanyName><commpanyDesc>16薪 TOP互联网公司 核心部门核心业务</commpanyDesc><posCount>16个职位</posCount></Job><Job><jobTitle>Golang高级工程师</jobTitle><jobSaray>20-40K/月</jobSaray><jobDemand>北京市 本科 3-5年</jobDemand><commpanyName>北京仕邦达人力资源有限公司</commpanyName><commpanyDesc>核心部门核心业务 TOP互联网公司 16薪</commpanyDesc><posCount>16个职位</posCount></Job><Job><jobTitle>Java leader</jobTitle><jobSaray>20-30K/月</jobSaray><jobDemand>北京市 本科 5-10年</jobDemand><commpanyName>北京红果科技有限公司</commpanyName><commpanyDesc>交通便利 五险一金</commpanyDesc><posCount>7个职位</posCount></Job><Job><jobTitle>招聘专员</jobTitle><jobSaray>12-15K/月</jobSaray><jobDemand>北京市 本科 1-3年</jobDemand><commpanyName>北京红果科技有限公司</commpanyName><commpanyDesc>交通便利 五险一金</commpanyDesc><posCount>7个职位</posCount></Job><Job><jobTitle>Java</jobTitle><jobSaray>25-30K/月</jobSaray><jobDemand>北京市 本科 5-10年</jobDemand><commpanyName>北京红果科技有限公司</commpanyName><commpanyDesc>交通便利 五险一金</commpanyDesc><posCount>7个职位</posCount></Job><Job><jobTitle>高级软件工程师</jobTitle><jobSaray>10-20K/月</jobSaray><jobDemand>重庆市 本科 3-5年</jobDemand><commpanyName>重庆臻联盛创科技发展有限公司</commpanyName><commpanyDesc>无</commpanyDesc><posCount>4个职位</posCount></Job><Job><jobTitle>高级前端工程师</jobTitle><jobSaray>8-16K/月</jobSaray><jobDemand>重庆市 本科 3-5年</jobDemand><commpanyName>重庆臻联盛创科技发展有限公司</commpanyName><commpanyDesc>无</commpanyDesc><posCount>4个职位</posCount></Job><Job><jobTitle>推荐算法负责人</jobTitle><jobSaray>10-20K/月</jobSaray><jobDemand>重庆市 本科 3-5年</jobDemand><commpanyName>重庆臻联盛创科技发展有限公司</commpanyName><commpanyDesc>无</commpanyDesc><posCount>4个职位</posCount></Job><Job><jobTitle>JAVA高级软件工程师</jobTitle><jobSaray>8-16K/月</jobSaray><jobDemand>重庆市 本科 3-5年</jobDemand><commpanyName>重庆臻联盛创科技发展有限公司</commpanyName><commpanyDesc>无</commpanyDesc><posCount>4个职位</posCount></Job><Job><jobTitle>系统架构师</jobTitle><jobSaray>16-22K/月</jobSaray><jobDemand>杭州市 大专 10年以上</jobDemand><commpanyName>浙江互灵物联科技有限公司</commpanyName><commpanyDesc>无</commpanyDesc><posCount>5个职位</posCount></Job><Job><jobTitle>测试工程师</jobTitle><jobSaray>8-16K/月</jobSaray><jobDemand>北京市 本科 1-3年</jobDemand><commpanyName>北京晶派科技有限公司</commpanyName><commpanyDesc>MIT大牛 带薪年假 工作居住证 腾讯谷歌投资 五险一金</commpanyDesc><posCount>9个职位</posCount></Job><Job><jobTitle>药物研发市场分析</jobTitle><jobSaray>8-16K/月</jobSaray><jobDemand>北京市 硕士 1-3年</jobDemand><commpanyName>北京晶派科技有限公司</commpanyName><commpanyDesc>MIT大牛 不断成长机会 带薪年假 腾讯谷歌投资 五险一金</commpanyDesc><posCount>9个职位</posCount></Job><Job><jobTitle>算法工程师</jobTitle><jobSaray>12-24K/月</jobSaray><jobDemand>北京市 硕士 1-3年</jobDemand><commpanyName>北京晶派科技有限公司</commpanyName><commpanyDesc>MIT大牛 不断成长机会 带薪年假 腾讯谷歌投资 五险一金</commpanyDesc><posCount>9个职位</posCount></Job><Job><jobTitle>药物研发算法实习生</jobTitle><jobSaray>3-5K/月</jobSaray><jobDemand>北京市 本科 1年以下</jobDemand><commpanyName>北京晶派科技有限公司</commpanyName><commpanyDesc>MIT大牛 不断成长机会 腾讯谷歌投资 五险一金</commpanyDesc><posCount>9个职位</posCount></Job><Job><jobTitle>小分子药物研发科学家</jobTitle><jobSaray>8-16K/月</jobSaray><jobDemand>北京市 硕士 1-3年</jobDemand><commpanyName>北京晶派科技有限公司</commpanyName><commpanyDesc>MIT大牛 不断成长机会 带薪年假 五险一金 腾讯谷歌投资</commpanyDesc><posCount>9个职位</posCount></Job><Job><jobTitle>生物医药研发科学家</jobTitle><jobSaray>8-16K/月</jobSaray><jobDemand>北京市 硕士 1-3年</jobDemand><commpanyName>北京晶派科技有限公司</commpanyName><commpanyDesc>无</commpanyDesc><posCount>9个职位</posCount></Job><Job><jobTitle>机器学习算法科学家</jobTitle><jobSaray>20-40K/月</jobSaray><jobDemand>北京市 硕士 1-3年</jobDemand><commpanyName>北京晶派科技有限公司</commpanyName><commpanyDesc>MIT大牛 不断成长机会 带薪年假 腾讯谷歌投资 五险一金</commpanyDesc><posCount>9个职位</posCount></Job><Job><jobTitle>Python后台开发</jobTitle><jobSaray>10-18K/月</jobSaray><jobDemand>北京市 本科 1-3年</jobDemand><commpanyName>北京晶派科技有限公司</commpanyName><commpanyDesc>不断成长机会 MIT大牛 带薪年假 工作居住证 五险一金</commpanyDesc><posCount>9个职位</posCount></Job><Job><jobTitle>药物研发科学家（计算机辅助药物设计）</jobTitle><jobSaray>20-40K/月</jobSaray><jobDemand>北京市 博士 3-5年</jobDemand><commpanyName>北京晶派科技有限公司</commpanyName><commpanyDesc>无</commpanyDesc><posCount>9个职位</posCount></Job><Job><jobTitle>软件测试工程师</jobTitle><jobSaray>20-25K/月</jobSaray><jobDemand>北京市 本科 3-5年</jobDemand><commpanyName>北京红果科技有限公司</commpanyName><commpanyDesc>交通便利 五险一金</commpanyDesc><posCount>7个职位</posCount></Job><Job><jobTitle>Java开发工程师</jobTitle><jobSaray>15-25K/月</jobSaray><jobDemand>广州市 本科 5-10年</jobDemand><commpanyName>北京智蓝信息科技有限公司</commpanyName><commpanyDesc>无</commpanyDesc><posCount>10个职位</posCount></Job><Job><jobTitle>C++开发工程师</jobTitle><jobSaray>15-25K/月</jobSaray><jobDemand>广州市 本科 5-10年</jobDemand><commpanyName>北京智蓝信息科技有限公司</commpanyName><commpanyDesc>不加班 假日多 外企-弹性工作制 周末</commpanyDesc><posCount>10个职位</posCount></Job><Job><jobTitle>算法工程师</jobTitle><jobSaray>15-30K/月</jobSaray><jobDemand>深圳市 硕士 3-5年</jobDemand><commpanyName>上海云猎人力资源有限公司</commpanyName><commpanyDesc>无</commpanyDesc><posCount>4个职位</posCount></Job><Job><jobTitle>Java开发（分布式高并发）</jobTitle><jobSaray>15-25K/月</jobSaray><jobDemand>广州市 本科 5-10年</jobDemand><commpanyName>北京智蓝信息科技有限公司</commpanyName><commpanyDesc>不加班 假日多 外企-弹性工作制 周末</commpanyDesc><posCount>10个职位</posCount></Job><Job><jobTitle>ｊａｖａ测试开发工程师</jobTitle><jobSaray>15-30K/月</jobSaray><jobDemand>北京市 本科 3-5年</jobDemand><commpanyName>北京凌卓咨询有限公司</commpanyName><commpanyDesc>外资-全球-强</commpanyDesc><posCount>1个职位</posCount></Job><Job><jobTitle>自动化测试工程师</jobTitle><jobSaray>15-25K/月</jobSaray><jobDemand>广州市 本科 5-10年</jobDemand><commpanyName>北京智蓝信息科技有限公司</commpanyName><commpanyDesc>不加班 周末 假日多 外企-弹性工作制</commpanyDesc><posCount>10个职位</posCount></Job><Job><jobTitle>系统工程师</jobTitle><jobSaray>15-25K/月</jobSaray><jobDemand>广州市 本科 5-10年</jobDemand><commpanyName>北京智蓝信息科技有限公司</commpanyName><commpanyDesc>外企-弹性工作制</commpanyDesc><posCount>10个职位</posCount></Job><Job><jobTitle>集成测试工程师</jobTitle><jobSaray>15-25K/月</jobSaray><jobDemand>广州市 本科 5-10年</jobDemand><commpanyName>北京智蓝信息科技有限公司</commpanyName><commpanyDesc>外企-弹性工作制</commpanyDesc><posCount>10个职位</posCount></Job><Job><jobTitle>C++开发工程师</jobTitle><jobSaray>15-25K/月</jobSaray><jobDemand>广州市 本科 5-10年</jobDemand><commpanyName>北京智蓝信息科技有限公司</commpanyName><commpanyDesc>外企-弹性工作制</commpanyDesc><posCount>10个职位</posCount></Job><Job><jobTitle>高级Java开发工程师</jobTitle><jobSaray>15-25K/月</jobSaray><jobDemand>广州市 本科 5-10年</jobDemand><commpanyName>北京智蓝信息科技有限公司</commpanyName><commpanyDesc>外企-弹性工作制</commpanyDesc><posCount>10个职位</posCount></Job><Job><jobTitle>Java开发工程师</jobTitle><jobSaray>15-25K/月</jobSaray><jobDemand>广州市 本科 5-10年</jobDemand><commpanyName>北京智蓝信息科技有限公司</commpanyName><commpanyDesc>外企-弹性工作制</commpanyDesc><posCount>10个职位</posCount></Job><Job><jobTitle>推荐算法工程师</jobTitle><jobSaray>30-60K/月</jobSaray><jobDemand>北京市 本科 3-5年</jobDemand><commpanyName>杭州千汇人力资源开发有限公司</commpanyName><commpanyDesc>晋升完善 团队大牛多 稳定</commpanyDesc><posCount>14个职位</posCount></Job><Job><jobTitle>引擎开发工程师</jobTitle><jobSaray>40-80K/月</jobSaray><jobDemand>北京市 本科 3-5年</jobDemand><commpanyName>杭州千汇人力资源开发有限公司</commpanyName><commpanyDesc>福利待遇好 晋升完善 团队大牛多 稳定</commpanyDesc><posCount>14个职位</posCount></Job><Job><jobTitle>用户增长经理</jobTitle><jobSaray>40-80K/月</jobSaray><jobDemand>北京市 本科 3-5年</jobDemand><commpanyName>杭州千汇人力资源开发有限公司</commpanyName><commpanyDesc>福利待遇好 晋升完善 团队大牛多 稳定</commpanyDesc><posCount>14个职位</posCount></Job><Job><jobTitle>大数据专家</jobTitle><jobSaray>50-100K/月</jobSaray><jobDemand>北京市 本科 3-5年</jobDemand><commpanyName>杭州千汇人力资源开发有限公司</commpanyName><commpanyDesc>大数据 大公司</commpanyDesc><posCount>14个职位</posCount></Job><Job><jobTitle>商业产品经理</jobTitle><jobSaray>30-60K/月</jobSaray><jobDemand>北京市 本科 3-5年</jobDemand><commpanyName>杭州千汇人力资源开发有限公司</commpanyName><commpanyDesc>福利待遇好 稳定 大公司</commpanyDesc><posCount>14个职位</posCount></Job><Job><jobTitle>IOT 产品总监</jobTitle><jobSaray>40-80K/月</jobSaray><jobDemand>北京市 本科 5-10年</jobDemand><commpanyName>杭州千汇人力资源开发有限公司</commpanyName><commpanyDesc>无</commpanyDesc><posCount>14个职位</posCount></Job><Job><jobTitle>产品总监</jobTitle><jobSaray>40-80K/月</jobSaray><jobDemand>北京市 本科 5-10年</jobDemand><commpanyName>杭州千汇人力资源开发有限公司</commpanyName><commpanyDesc>无</commpanyDesc><posCount>14个职位</posCount></Job><Job><jobTitle>CTO</jobTitle><jobSaray>60-120K/月</jobSaray><jobDemand>北京市 本科 3-5年</jobDemand><commpanyName>杭州千汇人力资源开发有限公司</commpanyName><commpanyDesc>无</commpanyDesc><posCount>14个职位</posCount></Job><Job><jobTitle>PHP开发leader</jobTitle><jobSaray>30-60K/月</jobSaray><jobDemand>北京市 本科 3-5年</jobDemand><commpanyName>杭州千汇人力资源开发有限公司</commpanyName><commpanyDesc>福利待遇好 团队大牛多</commpanyDesc><posCount>14个职位</posCount></Job><Job><jobTitle>Java高级开发工程师</jobTitle><jobSaray>20-30K/月</jobSaray><jobDemand>南京市 大专 3-5年</jobDemand><commpanyName>常州艾创网络科技有限公司</commpanyName><commpanyDesc>无</commpanyDesc><posCount>2个职位</posCount></Job><Job><jobTitle>web前端开发工程师</jobTitle><jobSaray>20-30K/月</jobSaray><jobDemand>南京市 大专 3-5年</jobDemand><commpanyName>常州艾创网络科技有限公司</commpanyName><commpanyDesc>无</commpanyDesc><posCount>2个职位</posCount></Job><Job><jobTitle>Camera算法工程师</jobTitle><jobSaray>15-25K/月</jobSaray><jobDemand>深圳市 本科 3-5年</jobDemand><commpanyName>深圳万普拉斯科技有限公司</commpanyName><commpanyDesc>无</commpanyDesc><posCount>2个职位</posCount></Job><Job><jobTitle>影像硬件工程师</jobTitle><jobSaray>15-25K/月</jobSaray><jobDemand>深圳市 本科 3-5年</jobDemand><commpanyName>深圳万普拉斯科技有限公司</commpanyName><commpanyDesc>无</commpanyDesc><posCount>2个职位</posCount></Job><Job><jobTitle>广告数据实习生</jobTitle><jobSaray>8-10K/月</jobSaray><jobDemand>北京市 本科 1年以下</jobDemand><commpanyName>北京字节跳动网络技术有限公司</commpanyName><commpanyDesc>年终红包 优秀团队 悠闲下午茶 住房补贴</commpanyDesc><posCount>26个职位</posCount></Job><Job><jobTitle>商业变现算法实习生</jobTitle><jobSaray>8-10K/月</jobSaray><jobDemand>北京市 本科 1年以下</jobDemand><commpanyName>北京字节跳动网络技术有限公司</commpanyName><commpanyDesc>优秀团队 悠闲下午茶 住房补贴</commpanyDesc><posCount>26个职位</posCount></Job><Job><jobTitle>后台开发实习生 - 核心广告系统</jobTitle><jobSaray>8-10K/月</jobSaray><jobDemand>北京市 本科 1年以下</jobDemand><commpanyName>北京字节跳动网络技术有限公司</commpanyName><commpanyDesc>优秀团队 悠闲下午茶 住房补贴</commpanyDesc><posCount>26个职位</posCount></Job><Job><jobTitle>前端开发实习生 - 核心广告系统</jobTitle><jobSaray>8-10K/月</jobSaray><jobDemand>北京市 本科 1年以下</jobDemand><commpanyName>北京字节跳动网络技术有限公司</commpanyName><commpanyDesc>优秀团队 悠闲下午茶 住房补贴</commpanyDesc><posCount>26个职位</posCount></Job><Job><jobTitle>高级后端开发工程师</jobTitle><jobSaray>20-40K/月</jobSaray><jobDemand>深圳市 本科 5-10年</jobDemand><commpanyName>上海云猎人力资源有限公司</commpanyName><commpanyDesc>无</commpanyDesc><posCount>4个职位</posCount></Job><Job><jobTitle>高级前端工程师</jobTitle><jobSaray>25-43K/月</jobSaray><jobDemand>深圳市 本科 5-10年</jobDemand><commpanyName>上海云猎人力资源有限公司</commpanyName><commpanyDesc>无</commpanyDesc><posCount>4个职位</posCount></Job><Job><jobTitle>PHP</jobTitle><jobSaray>15-20K/月</jobSaray><jobDemand>北京市 本科 1-3年</jobDemand><commpanyName>北京红果科技有限公司</commpanyName><commpanyDesc>交通便利 五险一金</commpanyDesc><posCount>7个职位</posCount></Job><Job><jobTitle>web前端工程师</jobTitle><jobSaray>20-25K/月</jobSaray><jobDemand>北京市 本科 3-5年</jobDemand><commpanyName>北京红果科技有限公司</commpanyName><commpanyDesc>五险一金 交通便利</commpanyDesc><posCount>7个职位</posCount></Job><Job><jobTitle>运营助理（实习岗）</jobTitle><jobSaray>3-5K/月</jobSaray><jobDemand>广州市 本科 应届生</jobDemand><commpanyName>广州仓云网络有限公司</commpanyName><commpanyDesc>带薪年假 弹性工作 岗位晋升 周末双休</commpanyDesc><posCount>1个职位</posCount></Job><Job><jobTitle>资深项目经理</jobTitle><jobSaray>10-20K/月</jobSaray><jobDemand>广州市 本科 1-3年</jobDemand><commpanyName>Phexus International Service Incorporated</commpanyName><commpanyDesc>13-14薪 17天年假每年2次 3-6个月调薪一次 分红 生活津贴</commpanyDesc><posCount>5个职位</posCount></Job><Job><jobTitle>资深IT翻译</jobTitle><jobSaray>10-20K/月</jobSaray><jobDemand>广州市 本科 1-3年</jobDemand><commpanyName>Phexus International Service Incorporated</commpanyName><commpanyDesc>13-14薪 17天年假每年2次 3-6个月调薪一次 分红 生活津贴</commpanyDesc><posCount>5个职位</posCount></Job><Job><jobTitle>资深测试</jobTitle><jobSaray>15-30K/月</jobSaray><jobDemand>广州市 本科 5-10年</jobDemand><commpanyName>Phexus International Service Incorporated</commpanyName><commpanyDesc>13-14薪 17天年假每年2次 3-6个月调薪一次 分红 生活津贴</commpanyDesc><posCount>5个职位</posCount></Job><Job><jobTitle>资深前端</jobTitle><jobSaray>10-20K/月</jobSaray><jobDemand>广州市 大专 1-3年</jobDemand><commpanyName>Phexus International Service Incorporated</commpanyName><commpanyDesc>13-14薪 17天年假每年2次 3-6个月调薪一次 分红 生活津贴</commpanyDesc><posCount>5个职位</posCount></Job><Job><jobTitle>[招聘 iOS 开发工程师(手机游戏方向...</jobTitle><jobSaray>8-16K/月</jobSaray><jobDemand>深圳市 本科 1年以下</jobDemand><commpanyName>深圳中博网络技术有限公司</commpanyName><commpanyDesc>年度旅游 定期体检 带薪年假 周末双休 五险一金</commpanyDesc><posCount>3个职位</posCount></Job><Job><jobTitle>[招聘 Android 开发工程师（手游...</jobTitle><jobSaray>8-16K/月</jobSaray><jobDemand>深圳市 本科 1年以下</jobDemand><commpanyName>深圳中博网络技术有限公司</commpanyName><commpanyDesc>带薪年假 定期体检 年度旅游 五险一金 周末双休</commpanyDesc><posCount>3个职位</posCount></Job><Job><jobTitle>资深PHP</jobTitle><jobSaray>10-20K/月</jobSaray><jobDemand>广州市 大专 1-3年</jobDemand><commpanyName>Phexus International Service Incorporated</commpanyName><commpanyDesc>17天年假每年2次 生活津贴 3-6个月调薪一次 13-14薪 分红</commpanyDesc><posCount>5个职位</posCount></Job><Job><jobTitle>U3D</jobTitle><jobSaray>7-14K/月</jobSaray><jobDemand>深圳市 本科 1年以下</jobDemand><commpanyName>深圳中博网络技术有限公司</commpanyName><commpanyDesc>海外手游 高配团队 鹅厂大神 双休福利好 六险一金</commpanyDesc><posCount>3个职位</posCount></Job><Job><jobTitle>算法工程师</jobTitle><jobSaray>8-12K/月</jobSaray><jobDemand>成都市 本科 1-3年</jobDemand><commpanyName>深圳市凌盟科技有限公司</commpanyName><commpanyDesc>带薪休假 岗位分红 绩效奖金 五险一金 下午茶</commpanyDesc><posCount>2个职位</posCount></Job><Job><jobTitle>iOS职位</jobTitle><jobSaray>15-20K/月</jobSaray><jobDemand>北京市 本科 1-3年</jobDemand><commpanyName>北京红果科技有限公司</commpanyName><commpanyDesc>交通便利 五险一金</commpanyDesc><posCount>7个职位</posCount></Job><Job><jobTitle>web前端开发工程师</jobTitle><jobSaray>8-15K/月</jobSaray><jobDemand>深圳市 本科 1-3年</jobDemand><commpanyName>深圳个人数据管理服务有限公司</commpanyName><commpanyDesc>无</commpanyDesc><posCount>1个职位</posCount></Job><Job><jobTitle>web前端开发工程师</jobTitle><jobSaray>15-25K/月</jobSaray><jobDemand>广州市 本科 5-10年</jobDemand><commpanyName>北京智蓝信息科技有限公司</commpanyName><commpanyDesc>不加班 假日多 外企-弹性工作制 周末</commpanyDesc><posCount>10个职位</posCount></Job><Job><jobTitle>基础架构师</jobTitle><jobSaray>25-40K/月</jobSaray><jobDemand>深圳市 本科 5-10年</jobDemand><commpanyName>上海云猎人力资源有限公司</commpanyName><commpanyDesc>无</commpanyDesc><posCount>4个职位</posCount></Job><Job><jobTitle>cobol工程师</jobTitle><jobSaray>7-13K/月</jobSaray><jobDemand>深圳市 本科 1-3年</jobDemand><commpanyName>深圳市雁联计算系统有限公司</commpanyName><commpanyDesc>金融系统 银行</commpanyDesc><posCount>1个职位</posCount></Job><Job><jobTitle>Java架构师</jobTitle><jobSaray>25-50K/月</jobSaray><jobDemand>北京市 本科 5-10年</jobDemand><commpanyName>武汉智寻天下科技有限公司</commpanyName><commpanyDesc>发展空间大 待遇优厚 扁平管理</commpanyDesc><posCount>1个职位</posCount></Job><Job><jobTitle>JAVA开发工程师</jobTitle><jobSaray>6-12K/月</jobSaray><jobDemand>北京市 本科 1-3年</jobDemand><commpanyName>北京行动智能科技有限公司</commpanyName><commpanyDesc>潜力巨大 创业公司 计算机视觉 人工智能</commpanyDesc><posCount>2个职位</posCount></Job><Job><jobTitle>.NET高级开发工程师</jobTitle><jobSaray>15-20K/月</jobSaray><jobDemand>上海市 本科 5-10年</jobDemand><commpanyName>上海途逸公寓管理有限公司</commpanyName><commpanyDesc>季度奖 商业医疗保险 补充公积金 上升空间 带薪病假</commpanyDesc><posCount>2个职位</posCount></Job><Job><jobTitle>互联网产品经理</jobTitle><jobSaray>15-20K/月</jobSaray><jobDemand>上海市 本科 5-10年</jobDemand><commpanyName>上海途逸公寓管理有限公司</commpanyName><commpanyDesc>带薪病假 补充公积金 商业医疗保险 上升空间 季度奖</commpanyDesc><posCount>2个职位</posCount></Job><Job><jobTitle>Java开发工程师</jobTitle><jobSaray>10-15K/月</jobSaray><jobDemand>上海市 本科 1-3年</jobDemand><commpanyName>上海开先软件有限公司</commpanyName><commpanyDesc>福利待遇好 年终奖金 晋升空间大 出国机会 弹性工作</commpanyDesc><posCount>3个职位</posCount></Job><Job><jobTitle>售前业务顾问</jobTitle><jobSaray>20-25K/月</jobSaray><jobDemand>上海市 本科 1-3年</jobDemand><commpanyName>上海开先软件有限公司</commpanyName><commpanyDesc>出国机会 年终奖金 晋升空间大 福利待遇好 弹性工作</commpanyDesc><posCount>3个职位</posCount></Job><Job><jobTitle>C语言高级开发工程师</jobTitle><jobSaray>15-25K/月</jobSaray><jobDemand>上海市 本科 1-3年</jobDemand><commpanyName>上海开先软件有限公司</commpanyName><commpanyDesc>管理规范 年终奖金 出国机会 福利待遇好 弹性工作</commpanyDesc><posCount>3个职位</posCount></Job><Job><jobTitle>【海外手游公司】SEM优化工程师</jobTitle><jobSaray>15-30K/月</jobSaray><jobDemand>成都市 大专 1-3年</jobDemand><commpanyName></commpanyName><commpanyDesc>分红 高薪 旅游 买房买车补贴 团建</commpanyDesc><posCount>6个职位</posCount></Job><Job><jobTitle>【海外手游公司】中高级php</jobTitle><jobSaray>20-35K/月</jobSaray><jobDemand>成都市 大专 1-3年</jobDemand><commpanyName>深圳国会科技有限公司</commpanyName><commpanyDesc>分红 高薪 旅游 买房买车补贴 团建</commpanyDesc><posCount>6个职位</posCount></Job><Job><jobTitle>【海外手游公司】游戏测试工程师</jobTitle><jobSaray>15-30K/月</jobSaray><jobDemand>成都市 大专 1-3年</jobDemand><commpanyName>深圳国会科技有限公司</commpanyName><commpanyDesc>分红 高薪 旅游 买房买车补贴 团建</commpanyDesc><posCount>6个职位</posCount></Job><Job><jobTitle>【海外手游公司】游戏ui（原画）设计师</jobTitle><jobSaray>18-35K/月</jobSaray><jobDemand>成都市 大专 1-3年</jobDemand><commpanyName>深圳国会科技有限公司</commpanyName><commpanyDesc>分红 高薪 旅游 买房买车补贴 团建</commpanyDesc><posCount>6个职位</posCount></Job><Job><jobTitle>【海外手游公司】服务端开发工程师</jobTitle><jobSaray>20-40K/月</jobSaray><jobDemand>成都市 大专 1-3年</jobDemand><commpanyName>深圳国会科技有限公司</commpanyName><commpanyDesc>分红 高薪 旅游 买房买车补贴 团建</commpanyDesc><posCount>6个职位</posCount></Job><Job><jobTitle>【海外手游公司20k-35k】cocos...</jobTitle><jobSaray>20-35K/月</jobSaray><jobDemand>成都市 大专 1-3年</jobDemand><commpanyName>深圳国会科技有限公司</commpanyName><commpanyDesc>分红 旅游 买房买车补贴 团建 高薪</commpanyDesc><posCount>6个职位</posCount></Job><Job><jobTitle>C++服务器开发工程师</jobTitle><jobSaray>12-24K/月</jobSaray><jobDemand>杭州市 本科 1-3年</jobDemand><commpanyName>杭州掌盟软件股份有限公司</commpanyName><commpanyDesc>架构设计 Linux C++</commpanyDesc><posCount>4个职位</posCount></Job><Job><jobTitle>C++客户端开发工程师</jobTitle><jobSaray>5-10K/月</jobSaray><jobDemand>杭州市 本科 1-3年</jobDemand><commpanyName>杭州掌盟软件股份有限公司</commpanyName><commpanyDesc>WinAPI-MFC 2008</commpanyDesc><posCount>4个职位</posCount></Job><Job><jobTitle>逆向工程师（破解）</jobTitle><jobSaray>7-14K/月</jobSaray><jobDemand>杭州市 本科 1-3年</jobDemand><commpanyName>杭州掌盟软件股份有限公司</commpanyName><commpanyDesc>HTML JS</commpanyDesc><posCount>4个职位</posCount></Job><Job><jobTitle>h5游戏开发工程师</jobTitle><jobSaray>7-14K/月</jobSaray><jobDemand>杭州市 本科 1-3年</jobDemand><commpanyName>杭州掌盟软件股份有限公司</commpanyName><commpanyDesc>开源jquery JavaScrip CSS HTML</commpanyDesc><posCount>4个职位</posCount></Job><Job><jobTitle>ASIC Physical Design...</jobTitle><jobSaray>1-1K/月</jobSaray><jobDemand>北京市 本科 10年以上</jobDemand><commpanyName>超威半导体（中国）有限公司</commpanyName><commpanyDesc>无</commpanyDesc><posCount>4个职位</posCount></Job><Job><jobTitle>SoC DFT Senior Engin...</jobTitle><jobSaray>1-1K/月</jobSaray><jobDemand>北京市 硕士 3-5年</jobDemand><commpanyName>超威半导体（中国）有限公司</commpanyName><commpanyDesc>无</commpanyDesc><posCount>4个职位</posCount></Job><Job><jobTitle>Sr. SoC Performance ...</jobTitle><jobSaray>1-1K/月</jobSaray><jobDemand>上海市 硕士 3-5年</jobDemand><commpanyName>超威半导体（中国）有限公司</commpanyName><commpanyDesc>无</commpanyDesc><posCount>4个职位</posCount></Job><Job><jobTitle>SoC Architect</jobTitle><jobSaray>1-1K/月</jobSaray><jobDemand>上海市 本科 10年以上</jobDemand><commpanyName>超威半导体（中国）有限公司</commpanyName><commpanyDesc>无</commpanyDesc><posCount>4个职位</posCount></Job><Job><jobTitle>移动开发工程师</jobTitle><jobSaray>8-16K/月</jobSaray><jobDemand>北京市 本科 1-3年</jobDemand><commpanyName>北京行动智能科技有限公司</commpanyName><commpanyDesc>潜力巨大 创业公司 计算机视觉 人工智能</commpanyDesc><posCount>2个职位</posCount></Job><Job><jobTitle>研发总监</jobTitle><jobSaray>25-45K/月</jobSaray><jobDemand>北京市 硕士 5-10年</jobDemand><commpanyName>北京北斗星辰人力资源顾问有限公司</commpanyName><commpanyDesc>五险一金-补充医疗 带薪年假</commpanyDesc><posCount>3个职位</posCount></Job><Job><jobTitle>中高级java工程师</jobTitle><jobSaray>20-35K/月</jobSaray><jobDemand>深圳市 本科 3-5年</jobDemand><commpanyName>友金所</commpanyName><commpanyDesc>高福利 友金所 知名金融科技公司</commpanyDesc><posCount>1个职位</posCount></Job><Job><jobTitle>前端开发工程师</jobTitle><jobSaray>6-10K/月</jobSaray><jobDemand>北京市 本科 1年以下</jobDemand><commpanyName>北京集客门信息技术有限公司</commpanyName><commpanyDesc>成员都很好 扁平管理 有很大提升空间</commpanyDesc><posCount>1个职位</posCount></Job><Job><jobTitle>资深Web后端开发工程师（Python）</jobTitle><jobSaray>12-24K/月</jobSaray><jobDemand>南京市 本科 3-5年</jobDemand><commpanyName>南京天数信息科技有限公司</commpanyName><commpanyDesc>无</commpanyDesc><posCount>2个职位</posCount></Job><Job><jobTitle>前端开发工程师</jobTitle><jobSaray>10-20K/月</jobSaray><jobDemand>南京市 本科 3-5年</jobDemand><commpanyName>南京天数信息科技有限公司</commpanyName><commpanyDesc>无</commpanyDesc><posCount>2个职位</posCount></Job><Job><jobTitle>Linux C/C++ 开发工程师</jobTitle><jobSaray>10-20K/月</jobSaray><jobDemand>上海市 大专 1-3年</jobDemand><commpanyName>上海广升信息技术股份有限公司</commpanyName><commpanyDesc>无</commpanyDesc><posCount>2个职位</posCount></Job><Job><jobTitle>Linux C/C++ 开发工程师（车联...</jobTitle><jobSaray>15-25K/月</jobSaray><jobDemand>上海市 大专 3-5年</jobDemand><commpanyName>上海广升信息技术股份有限公司</commpanyName><commpanyDesc>无</commpanyDesc><posCount>2个职位</posCount></Job><Job><jobTitle>Java开发工程师</jobTitle><jobSaray>10-20K/月</jobSaray><jobDemand>广州市 本科 3-5年</jobDemand><commpanyName>云宏信息科技股份有限公司</commpanyName><commpanyDesc>云计算 软件研发 j2ee Java</commpanyDesc><posCount>8个职位</posCount></Job><Job><jobTitle>软件测试工程师</jobTitle><jobSaray>8-15K/月</jobSaray><jobDemand>广州市 本科 1-3年</jobDemand><commpanyName>云宏信息科技股份有限公司</commpanyName><commpanyDesc>linux 功能测试 性能测试 软件测试</commpanyDesc><posCount>8个职位</posCount></Job><Job><jobTitle>需求经理</jobTitle><jobSaray>15-30K/月</jobSaray><jobDemand>广州市 本科 5-10年</jobDemand><commpanyName>云宏信息科技股份有限公司</commpanyName><commpanyDesc>产品设计 Axure 需求管理 需求调研 云计算</commpanyDesc><posCount>8个职位</posCount></Job><Job><jobTitle>虚拟化开发工程师</jobTitle><jobSaray>15-30K/月</jobSaray><jobDemand>广州市 本科 3-5年</jobDemand><commpanyName>云宏信息科技股份有限公司</commpanyName><commpanyDesc>虚拟化 c-c++ Python linux内核 云计算</commpanyDesc><posCount>8个职位</posCount></Job><Job><jobTitle>linux系统开发工程师</jobTitle><jobSaray>15-30K/月</jobSaray><jobDemand>广州市 本科 5-10年</jobDemand><commpanyName>云宏信息科技股份有限公司</commpanyName><commpanyDesc>操作系统开发 Python shell 云计算 Iaas</commpanyDesc><posCount>8个职位</posCount></Job><Job><jobTitle>产品经理</jobTitle><jobSaray>15-30K/月</jobSaray><jobDemand>广州市 本科 3-5年</jobDemand><commpanyName>云宏信息科技股份有限公司</commpanyName><commpanyDesc>产品运营 云计算</commpanyDesc><posCount>8个职位</posCount></Job><Job><jobTitle>高级质量管理工程师</jobTitle><jobSaray>15-30K/月</jobSaray><jobDemand>广州市 本科 5-10年</jobDemand><commpanyName>云宏信息科技股份有限公司</commpanyName><commpanyDesc>云计算 QA 性能测试 功能测试 软件测试</commpanyDesc><posCount>8个职位</posCount></Job><Job><jobTitle>C++开发工程师</jobTitle><jobSaray>15-25K/月</jobSaray><jobDemand>广州市 本科 3-5年</jobDemand><commpanyName>云宏信息科技股份有限公司</commpanyName><commpanyDesc>c++ qss设计 VS t-reator</commpanyDesc><posCount>8个职位</posCount></Job><Job><jobTitle>JAVA后台资深工程师/技术专家</jobTitle><jobSaray>30-50K/月</jobSaray><jobDemand>上海市 本科 5-10年</jobDemand><commpanyName>爱奇艺上海分公司</commpanyName><commpanyDesc>弹性工作 技术过硬 潜力产品</commpanyDesc><posCount>3个职位</posCount></Job><Job><jobTitle>资深ios开发工程师（上海）</jobTitle><jobSaray>30-50K/月</jobSaray><jobDemand>上海市 本科 5-10年</jobDemand><commpanyName>爱奇艺上海分公司</commpanyName><commpanyDesc>弹性工作 技术过硬 潜力产品</commpanyDesc><posCount>3个职位</posCount></Job><Job><jobTitle>资深Android开发工程师/技术专家（...</jobTitle><jobSaray>30-50K/月</jobSaray><jobDemand>上海市 本科 5-10年</jobDemand><commpanyName>爱奇艺上海分公司</commpanyName><commpanyDesc>弹性工作 技术过硬</commpanyDesc><posCount>3个职位</posCount></Job><Job><jobTitle>嵌入式C开发</jobTitle><jobSaray>13-20K/月</jobSaray><jobDemand>北京市 大专 1-3年</jobDemand><commpanyName>文思海辉技术有限公司</commpanyName><commpanyDesc>免费晚餐 五险一金商业医疗保险 华为华三优秀团队 新项目 分流器核心阶段开发</commpanyDesc><posCount>30个职位</posCount></Job><Job><jobTitle>java开发</jobTitle><jobSaray>12-15K/月</jobSaray><jobDemand>北京市 大专 1-3年</jobDemand><commpanyName>文思海辉技术有限公司</commpanyName><commpanyDesc>微服务 五险一金商业医疗保险 餐饮补贴 分布式技术 独角兽地图企业</commpanyDesc><posCount>30个职位</posCount></Job><Job><jobTitle>web前端</jobTitle><jobSaray>12-15K/月</jobSaray><jobDemand>北京市 大专 1-3年</jobDemand><commpanyName>文思海辉技术有限公司</commpanyName><commpanyDesc>海量数据 独角兽地图企业 react 业内领先的车载导航</commpanyDesc><posCount>30个职位</posCount></Job><Job><jobTitle>.net开发（实习）</jobTitle><jobSaray>2-4K/月</jobSaray><jobDemand>北京市 本科 应届生</jobDemand><commpanyName>北京北森云计算股份有限公司</commpanyName><commpanyDesc>技术大牛 外地同学提供宿舍 一对一导师</commpanyDesc><posCount>3个职位</posCount></Job><Job><jobTitle>.net架构师</jobTitle><jobSaray>25-50K/月</jobSaray><jobDemand>北京市 本科 5-10年</jobDemand><commpanyName>北京北森云计算股份有限公司</commpanyName><commpanyDesc>无</commpanyDesc><posCount>3个职位</posCount></Job><Job><jobTitle>高级web前端开发工程师</jobTitle><jobSaray>25-50K/月</jobSaray><jobDemand>北京市 本科 5-10年</jobDemand><commpanyName>北京北森云计算股份有限公司</commpanyName><commpanyDesc>无</commpanyDesc><posCount>3个职位</posCount></Job><Job><jobTitle>前端开发工程师</jobTitle><jobSaray>15-25K/月</jobSaray><jobDemand>北京市 本科 5-10年</jobDemand><commpanyName>中国金融在线集团（金融界）</commpanyName><commpanyDesc>核心项目 核心业务 平台稳定 上市公司</commpanyDesc><posCount>5个职位</posCount></Job><Job><jobTitle>测试工程师（app方向）</jobTitle><jobSaray>15-25K/月</jobSaray><jobDemand>北京市 本科 3-5年</jobDemand><commpanyName>中国金融在线集团（金融界）</commpanyName><commpanyDesc>核心项目 核心业务 平台稳定 上市公司</commpanyDesc><posCount>5个职位</posCount></Job><Job><jobTitle>JAVA工程师</jobTitle><jobSaray>15-25K/月</jobSaray><jobDemand>北京市 本科 3-5年</jobDemand><commpanyName>中国金融在线集团（金融界）</commpanyName><commpanyDesc>上市公司 核心项目 核心业务 平台稳定</commpanyDesc><posCount>5个职位</posCount></Job><Job><jobTitle>Java开发工程师</jobTitle><jobSaray>8-14K/月</jobSaray><jobDemand>西安市 大专 3-5年</jobDemand><commpanyName>中软国际科技服务有限公司西安分公司</commpanyName><commpanyDesc>带薪年假 晋升空间 五险一金</commpanyDesc><posCount>3个职位</posCount></Job><Job><jobTitle>web前端开发</jobTitle><jobSaray>7-14K/月</jobSaray><jobDemand>西安市 大专 3-5年</jobDemand><commpanyName>中软国际科技服务有限公司西安分公司</commpanyName><commpanyDesc>带薪年假 晋升空间 五险一金</commpanyDesc><posCount>3个职位</posCount></Job><Job><jobTitle>前端开发（高级）工程师 - 抖音/火山</jobTitle><jobSaray>25-50K/月</jobSaray><jobDemand>北京市 本科 3-5年</jobDemand><commpanyName>北京字节跳动网络技术有限公司</commpanyName><commpanyDesc>扁平管理 六险一金-高薪期权 悠闲下午茶 住房补贴 租房补贴-带薪休假</commpanyDesc><posCount>26个职位</posCount></Job><Job><jobTitle>前端开发高级工程师</jobTitle><jobSaray>25-50K/月</jobSaray><jobDemand>北京市 本科 3-5年</jobDemand><commpanyName>北京字节跳动网络技术有限公司</commpanyName><commpanyDesc>扁平管理 住房补贴 六险一金-高薪期权 悠闲下午茶 租房补贴-带薪休假</commpanyDesc><posCount>26个职位</posCount></Job><Job><jobTitle>测试工程师</jobTitle><jobSaray>20-40K/月</jobSaray><jobDemand>北京市 本科 1-3年</jobDemand><commpanyName>北京字节跳动网络技术有限公司</commpanyName><commpanyDesc>扁平管理 悠闲下午茶 六险一金-高薪期权 租房补贴-带薪休假</commpanyDesc><posCount>26个职位</posCount></Job><Job><jobTitle>测试开发工程师 - 客户端专项</jobTitle><jobSaray>20-40K/月</jobSaray><jobDemand>北京市 本科 3-5年</jobDemand><commpanyName>北京字节跳动网络技术有限公司</commpanyName><commpanyDesc>各种福利 房补 六险一金-高薪期权 租房补贴-带薪休假</commpanyDesc><posCount>26个职位</posCount></Job><Job><jobTitle>图像算法工程师</jobTitle><jobSaray>15-20K/月</jobSaray><jobDemand>武汉市 本科 1-3年</jobDemand><commpanyName>武汉真元生物数据有限公司</commpanyName><commpanyDesc>员工宿舍 通讯补贴 交通补贴 五险一金</commpanyDesc><posCount>1个职位</posCount></Job><Job><jobTitle>高通DSP编程高手</jobTitle><jobSaray>100-200K/月</jobSaray><jobDemand>北京市 本科 5-10年</jobDemand><commpanyName>网易</commpanyName><commpanyDesc>大厂</commpanyDesc><posCount>1个职位</posCount></Job><Job><jobTitle>北京-高级Java工程师</jobTitle><jobSaray>25-45K/月</jobSaray><jobDemand>北京市 本科 3-5年</jobDemand><commpanyName>北京朗动科技有限公司-乐动力</commpanyName><commpanyDesc>阿里巴巴平台 三餐健身房</commpanyDesc><posCount>2个职位</posCount></Job><Job><jobTitle>C++开发工程师</jobTitle><jobSaray>15-30K/月</jobSaray><jobDemand>北京市 本科 1-3年</jobDemand><commpanyName>禾多科技（北京）有限公司</commpanyName><commpanyDesc>无</commpanyDesc><posCount>1个职位</posCount></Job><Job><jobTitle>C++开发工程师</jobTitle><jobSaray>6-12K/月</jobSaray><jobDemand>武汉市 大专 应届生</jobDemand><commpanyName>武汉思托福科技有限公司</commpanyName><commpanyDesc>出国旅游 年终奖 带薪年假 五险一金</commpanyDesc><posCount>1个职位</posCount></Job><Job><jobTitle>Hadoop开发工程师</jobTitle><jobSaray>20-35K/月</jobSaray><jobDemand>北京市 本科 3-5年</jobDemand><commpanyName>秒针信息技术有限公司</commpanyName><commpanyDesc>无</commpanyDesc><posCount>3个职位</posCount></Job><Job><jobTitle>Hadoop平台开发工程师</jobTitle><jobSaray>20-35K/月</jobSaray><jobDemand>北京市 本科 3-5年</jobDemand><commpanyName>秒针信息技术有限公司</commpanyName><commpanyDesc>学习型组织</commpanyDesc><posCount>3个职位</posCount></Job><Job><jobTitle>高级Java开发工程师</jobTitle><jobSaray>20-35K/月</jobSaray><jobDemand>北京市 本科 3-5年</jobDemand><commpanyName>秒针信息技术有限公司</commpanyName><commpanyDesc>重视创新 学习型组织 重视技术 大牛多</commpanyDesc><posCount>3个职位</posCount></Job><Job><jobTitle>JAVA高级软件工程师</jobTitle><jobSaray>8-13K/月</jobSaray><jobDemand>长沙市 本科 5-10年</jobDemand><commpanyName>瑞斯康微电子(深圳)有限公司湖南分公司</commpanyName><commpanyDesc>五险一金 美味的工作餐及水果 节日福利 员工旅游 周末双休</commpanyDesc><posCount>2个职位</posCount></Job><Job><jobTitle>C++软件工程师</jobTitle><jobSaray>6-10K/月</jobSaray><jobDemand>长沙市 本科 1-3年</jobDemand><commpanyName>瑞斯康微电子(深圳)有限公司湖南分公司</commpanyName><commpanyDesc>节日福利 五险一金 美味的工作餐及水果 员工旅游 周末双休</commpanyDesc><posCount>2个职位</posCount></Job><Job><jobTitle>Java web后台开发高级工程师</jobTitle><jobSaray>15-23K/月</jobSaray><jobDemand>上海市 本科 5-10年</jobDemand><commpanyName>上海容智信息技术有限公司</commpanyName><commpanyDesc>MySQL Redis hibernate Spring</commpanyDesc><posCount>1个职位</posCount></Job><Job><jobTitle>区块链高级研发工程师</jobTitle><jobSaray>20-40K/月</jobSaray><jobDemand>深圳市 本科 3-5年</jobDemand><commpanyName>深圳小步网络科技有限公司</commpanyName><commpanyDesc>弹性上班 技术导向 期权 薪水丰厚</commpanyDesc><posCount>2个职位</posCount></Job><Job><jobTitle>后台开发工程师</jobTitle><jobSaray>20-40K/月</jobSaray><jobDemand>深圳市 本科 3-5年</jobDemand><commpanyName>深圳小步网络科技有限公司</commpanyName><commpanyDesc>技术导向 期权 薪水丰厚 弹性上班</commpanyDesc><posCount>2个职位</posCount></Job><Job><jobTitle>游戏项目助理</jobTitle><jobSaray>8-10K/月</jobSaray><jobDemand>上海市 本科 1-3年</jobDemand><commpanyName>上海魔麟网络科技有限公司</commpanyName><commpanyDesc>无</commpanyDesc><posCount>2个职位</posCount></Job><Job><jobTitle>FLASH AS3开发工程师</jobTitle><jobSaray>10-20K/月</jobSaray><jobDemand>上海市 本科 1-3年</jobDemand><commpanyName>上海魔麟网络科技有限公司</commpanyName><commpanyDesc>无</commpanyDesc><posCount>2个职位</posCount></Job><Job><jobTitle>ios客户端开发工程师</jobTitle><jobSaray>15-25K/月</jobSaray><jobDemand>北京市 本科 3-5年</jobDemand><commpanyName>全悉科技（北京）有限公司</commpanyName><commpanyDesc>餐补</commpanyDesc><posCount>2个职位</posCount></Job><Job><jobTitle>安卓开发工程师</jobTitle><jobSaray>15-25K/月</jobSaray><jobDemand>北京市 本科 3-5年</jobDemand><commpanyName>全悉科技（北京）有限公司</commpanyName><commpanyDesc>餐补</commpanyDesc><posCount>2个职位</posCount></Job><Job><jobTitle>SAP实施推广顾问</jobTitle><jobSaray>15-30K/月</jobSaray><jobDemand>郑州市 本科 5-10年</jobDemand><commpanyName>陕西埃普沃企业管理咨询有限公司</commpanyName><commpanyDesc>薪酬福利好</commpanyDesc><posCount>6个职位</posCount></Job><Job><jobTitle>cocos客户端程序员</jobTitle><jobSaray>7-14K/月</jobSaray><jobDemand>厦门市 本科 1-3年</jobDemand><commpanyName>厦门景迅网络科技有限公司</commpanyName><commpanyDesc>无</commpanyDesc><posCount>2个职位</posCount></Job><Job><jobTitle>用户运营经理</jobTitle><jobSaray>15-30K/月</jobSaray><jobDemand>北京市 本科 3-5年</jobDemand><commpanyName>陕西埃普沃企业管理咨询有限公司</commpanyName><commpanyDesc>发展空间大 薪酬福利好</commpanyDesc><posCount>6个职位</posCount></Job><Job><jobTitle>内容运营经理</jobTitle><jobSaray>15-30K/月</jobSaray><jobDemand>北京市 本科 3-5年</jobDemand><commpanyName>陕西埃普沃企业管理咨询有限公司</commpanyName><commpanyDesc>发展空间大 薪酬福利好</commpanyDesc><posCount>6个职位</posCount></Job><Job><jobTitle>产品专家</jobTitle><jobSaray>30-50K/月</jobSaray><jobDemand>杭州市 本科 3-5年</jobDemand><commpanyName>陕西埃普沃企业管理咨询有限公司</commpanyName><commpanyDesc>发展空间大 薪酬福利好</commpanyDesc><posCount>6个职位</posCount></Job><Job><jobTitle>智能运维专家</jobTitle><jobSaray>30-60K/月</jobSaray><jobDemand>北京市 本科 5-10年</jobDemand><commpanyName>陕西埃普沃企业管理咨询有限公司</commpanyName><commpanyDesc>发展空间大 薪酬福利好</commpanyDesc><posCount>6个职位</posCount></Job><Job><jobTitle>资深运维研发工程师</jobTitle><jobSaray>30-50K/月</jobSaray><jobDemand>杭州市 本科 5-10年</jobDemand><commpanyName>陕西埃普沃企业管理咨询有限公司</commpanyName><commpanyDesc>发展空间大 薪酬福利好</commpanyDesc><posCount>6个职位</posCount></Job><Job><jobTitle>自动驾驶软件开发</jobTitle><jobSaray>15-25K/月</jobSaray><jobDemand>上海市 本科 5-10年</jobDemand><commpanyName>Johnhawkins</commpanyName><commpanyDesc>无</commpanyDesc><posCount>5个职位</posCount></Job><Job><jobTitle>图像感知算法嵌入式开发工程师</jobTitle><jobSaray>15-30K/月</jobSaray><jobDemand>上海市 本科 5-10年</jobDemand><commpanyName>Johnhawkins</commpanyName><commpanyDesc>无</commpanyDesc><posCount>5个职位</posCount></Job><Job><jobTitle>决策与规划算法开发</jobTitle><jobSaray>20-40K/月</jobSaray><jobDemand>上海市 本科 5-10年</jobDemand><commpanyName>Johnhawkins</commpanyName><commpanyDesc>无</commpanyDesc><posCount>5个职位</posCount></Job><Job><jobTitle>OTA架构师/OTA Architect</jobTitle><jobSaray>20-40K/月</jobSaray><jobDemand>上海市 本科 5-10年</jobDemand><commpanyName>Johnhawkins</commpanyName><commpanyDesc>无</commpanyDesc><posCount>5个职位</posCount></Job><Job><jobTitle>智能网联系统高级经理</jobTitle><jobSaray>30-50K/月</jobSaray><jobDemand>上海市 本科 5-10年</jobDemand><commpanyName>Johnhawkins</commpanyName><commpanyDesc>系统 车联网</commpanyDesc><posCount>5个职位</posCount></Job><Job><jobTitle>资深java开发工程师</jobTitle><jobSaray>15-20K/月</jobSaray><jobDemand>上海市 大专 10年以上</jobDemand><commpanyName>上海普加软件有限公司</commpanyName><commpanyDesc>定期体检 节日福利 每年多次调薪 年底双薪 五险一金</commpanyDesc><posCount>6个职位</posCount></Job><Job><jobTitle>PC/安卓/iOS客户端/逆向协yi分析</jobTitle><jobSaray>5-10K/月</jobSaray><jobDemand>阜阳市 中技 1-3年</jobDemand><commpanyName>启成瑞丰网游有限公司</commpanyName><commpanyDesc>带薪休假 包吃住 产品推出提成+保底 工作自由-休息时间充</commpanyDesc><posCount>2个职位</posCount></Job><Job><jobTitle>前端网页开发</jobTitle><jobSaray>3-6K/月</jobSaray><jobDemand>阜阳市 中技 1-3年</jobDemand><commpanyName>启成瑞丰网游有限公司</commpanyName><commpanyDesc>包吃住 产品推出提成+保底 工作自由-休息时间充</commpanyDesc><posCount>2个职位</posCount></Job><Job><jobTitle>前端开发工程师</jobTitle><jobSaray>10-20K/月</jobSaray><jobDemand>北京市 本科 1-3年</jobDemand><commpanyName>北京格上添富科技发展有限公司</commpanyName><commpanyDesc>不打卡-弹性工作</commpanyDesc><posCount>4个职位</posCount></Job><Job><jobTitle>后台研发leader</jobTitle><jobSaray>30-50K/月</jobSaray><jobDemand>北京市 本科 3-5年</jobDemand><commpanyName>北京仕邦达人力资源有限公司</commpanyName><commpanyDesc>TOP4互联网公司 核心部门核心业务 没有给不到 只有想不到</commpanyDesc><posCount>16个职位</posCount></Job><Job><jobTitle>python开发工程师</jobTitle><jobSaray>25-50K/月</jobSaray><jobDemand>北京市 本科 3-5年</jobDemand><commpanyName>北京仕邦达人力资源有限公司</commpanyName><commpanyDesc>TOP4互联网公司 核心部门核心业务 没有给不到 只有想不到</commpanyDesc><posCount>16个职位</posCount></Job><Job><jobTitle>服务器工程师</jobTitle><jobSaray>25-50K/月</jobSaray><jobDemand>北京市 本科 3-5年</jobDemand><commpanyName>北京仕邦达人力资源有限公司</commpanyName><commpanyDesc>TOP4互联网公司 核心部门核心业务 没有给不到 只有想不到</commpanyDesc><posCount>16个职位</posCount></Job><Job><jobTitle>机器学习算法工程师</jobTitle><jobSaray>25-50K/月</jobSaray><jobDemand>北京市 本科 3-5年</jobDemand><commpanyName>北京仕邦达人力资源有限公司</commpanyName><commpanyDesc>TOP4互联网公司 核心部门核心业务 没有给不到 只有想不到</commpanyDesc><posCount>16个职位</posCount></Job><Job><jobTitle>自然语言处理/ NLP工程师</jobTitle><jobSaray>25-50K/月</jobSaray><jobDemand>北京市 本科 3-5年</jobDemand><commpanyName>北京仕邦达人力资源有限公司</commpanyName><commpanyDesc>TOP4互联网公司 核心部门核心业务 没有给不到 只有想不到</commpanyDesc><posCount>16个职位</posCount></Job><Job><jobTitle>JAVA架构工程师</jobTitle><jobSaray>25-50K/月</jobSaray><jobDemand>北京市 本科 3-5年</jobDemand><commpanyName>北京仕邦达人力资源有限公司</commpanyName><commpanyDesc>TOP4互联网公司 核心部门核心业务 没有给不到 只有想不到</commpanyDesc><posCount>16个职位</posCount></Job><Job><jobTitle>客户端开发工程师</jobTitle><jobSaray>10-15K/月</jobSaray><jobDemand>北京市 本科 1-3年</jobDemand><commpanyName>北京格上添富科技发展有限公司</commpanyName><commpanyDesc>不打卡-弹性工作</commpanyDesc><posCount>4个职位</posCount></Job><Job><jobTitle>搜索/推荐广告算法(041438)</jobTitle><jobSaray>25-50K/月</jobSaray><jobDemand>北京市 本科 3-5年</jobDemand><commpanyName>北京仕邦达人力资源有限公司</commpanyName><commpanyDesc>只有想不到 没有给不到</commpanyDesc><posCount>16个职位</posCount></Job><Job><jobTitle>高级Python研发工程师</jobTitle><jobSaray>20-35K/月</jobSaray><jobDemand>北京市 本科 3-5年</jobDemand><commpanyName>北京格上添富科技发展有限公司</commpanyName><commpanyDesc>python 不打卡-弹性工作</commpanyDesc><posCount>4个职位</posCount></Job><Job><jobTitle>反作弊算法工程师</jobTitle><jobSaray>20-40K/月</jobSaray><jobDemand>北京市 本科 3-5年</jobDemand><commpanyName>北京仕邦达人力资源有限公司</commpanyName><commpanyDesc>核心部门核心业务 TOP4互联网公司 只有想不到 没有给不到</commpanyDesc><posCount>16个职位</posCount></Job><Job><jobTitle>React前端开发工程师</jobTitle><jobSaray>10-15K/月</jobSaray><jobDemand>北京市 本科 1-3年</jobDemand><commpanyName>北京格上添富科技发展有限公司</commpanyName><commpanyDesc>reactjs 不打卡-弹性工作</commpanyDesc><posCount>4个职位</posCount></Job><Job><jobTitle>后端工程师</jobTitle><jobSaray>7-14K/月</jobSaray><jobDemand>武汉市 本科 3-5年</jobDemand><commpanyName>武汉光谷联合集团有限公司</commpanyName><commpanyDesc>无</commpanyDesc><posCount>1个职位</posCount></Job><Job><jobTitle>嵌入式软件（实习生）</jobTitle><jobSaray>1-2K/月</jobSaray><jobDemand>苏州市 本科 应届生</jobDemand><commpanyName>苏州臻翌光电技术有限公司</commpanyName><commpanyDesc>无</commpanyDesc><posCount>3个职位</posCount></Job><Job><jobTitle>嵌入式软件工程师</jobTitle><jobSaray>3-4K/月</jobSaray><jobDemand>苏州市 本科 1-3年</jobDemand><commpanyName>苏州臻翌光电技术有限公司</commpanyName><commpanyDesc>无</commpanyDesc><posCount>3个职位</posCount></Job><Job><jobTitle>嵌入式软件工程师</jobTitle><jobSaray>2-3K/月</jobSaray><jobDemand>苏州市 本科 1-3年</jobDemand><commpanyName>苏州臻翌光电技术有限公司</commpanyName><commpanyDesc>无</commpanyDesc><posCount>3个职位</posCount></Job><Job><jobTitle>Python开发工程师</jobTitle><jobSaray>20-40K/月</jobSaray><jobDemand>上海市 本科 1-3年</jobDemand><commpanyName>平纳科(上海)信息咨询有限公司</commpanyName><commpanyDesc>弹性上下班 高薪 六险一金 人工智能 外企</commpanyDesc><posCount>3个职位</posCount></Job><Job><jobTitle>web前端工程师</jobTitle><jobSaray>20-40K/月</jobSaray><jobDemand>上海市 本科 1-3年</jobDemand><commpanyName>平纳科(上海)信息咨询有限公司</commpanyName><commpanyDesc>人工智能 弹性上下班 六险一金 高薪 外企</commpanyDesc><posCount>3个职位</posCount></Job><Job><jobTitle>Java开发工程师</jobTitle><jobSaray>20-40K/月</jobSaray><jobDemand>上海市 本科 3-5年</jobDemand><commpanyName>平纳科(上海)信息咨询有限公司</commpanyName><commpanyDesc>六险一金 弹性上下班 高薪 外企</commpanyDesc><posCount>3个职位</posCount></Job><Job><jobTitle>cocos客户端程序员（厦门）</jobTitle><jobSaray>3-6K/月</jobSaray><jobDemand>厦门市 大专 应届生</jobDemand><commpanyName>厦门景迅网络科技有限公司</commpanyName><commpanyDesc>无</commpanyDesc><posCount>2个职位</posCount></Job><Job><jobTitle>Java开发工程师</jobTitle><jobSaray>4-6K/月</jobSaray><jobDemand>苏州市 大专 1-3年</jobDemand><commpanyName>苏州安软信息科技有限公司</commpanyName><commpanyDesc>无</commpanyDesc><posCount>2个职位</posCount></Job><Job><jobTitle>Java中级研发工程师</jobTitle><jobSaray>7-12K/月</jobSaray><jobDemand>苏州市 大专 3-5年</jobDemand><commpanyName>苏州安软信息科技有限公司</commpanyName><commpanyDesc>无</commpanyDesc><posCount>2个职位</posCount></Job><Job><jobTitle>openerp开发工程师</jobTitle><jobSaray>15-28K/月</jobSaray><jobDemand>深圳市 大专 1-3年</jobDemand><commpanyName>深圳市有芯电子有限公司</commpanyName><commpanyDesc>无</commpanyDesc><posCount>3个职位</posCount></Job><Job><jobTitle>odoo开发工程师</jobTitle><jobSaray>15-28K/月</jobSaray><jobDemand>深圳市 大专 1-3年</jobDemand><commpanyName>深圳市有芯电子有限公司</commpanyName><commpanyDesc>无</commpanyDesc><posCount>3个职位</posCount></Job><Job><jobTitle>python工程师</jobTitle><jobSaray>15-28K/月</jobSaray><jobDemand>深圳市 大专 1-3年</jobDemand><commpanyName>深圳市有芯电子有限公司</commpanyName><commpanyDesc>无</commpanyDesc><posCount>3个职位</posCount></Job><Job><jobTitle>算法工程师</jobTitle><jobSaray>15-30K/月</jobSaray><jobDemand>北京市 本科 1-3年</jobDemand><commpanyName>北京哥大诺博教育科技股份有限公司</commpanyName><commpanyDesc>职业幸福感高 团队领导都nice 自适应 机器学习 填补行业空白</commpanyDesc><posCount>4个职位</posCount></Job><Job><jobTitle>Linux运维经理</jobTitle><jobSaray>15-25K/月</jobSaray><jobDemand>北京市 大专 3-5年</jobDemand><commpanyName>壕鑫互联（北京）网络科技有限公司</commpanyName><commpanyDesc>Python Perl shell Linux</commpanyDesc><posCount>2个职位</posCount></Job><Job><jobTitle>Java</jobTitle><jobSaray>10-16K/月</jobSaray><jobDemand>北京市 大专 3-5年</jobDemand><commpanyName>壕鑫互联（北京）网络科技有限公司</commpanyName><commpanyDesc>olang NodeJs</commpanyDesc><posCount>2个职位</posCount></Job><Job><jobTitle>android开发工程师</jobTitle><jobSaray>6-10K/月</jobSaray><jobDemand>漯河市 大专 1-3年</jobDemand><commpanyName>漯河江山天安新型建材有限公司</commpanyName><commpanyDesc>餐补 免费住宿 五险一金</commpanyDesc><posCount>1个职位</posCount></Job><Job><jobTitle>通信软件技术支持工程师</jobTitle><jobSaray>4-6K/月</jobSaray><jobDemand>北京市 本科 应届生</jobDemand><commpanyName>北京天地益星通信软件有限公司</commpanyName><commpanyDesc>无</commpanyDesc><posCount>3个职位</posCount></Job><Job><jobTitle>PHP开发工程师</jobTitle><jobSaray>4-6K/月</jobSaray><jobDemand>北京市 本科 应届生</jobDemand><commpanyName>北京天地益星通信软件有限公司</commpanyName><commpanyDesc>无</commpanyDesc><posCount>3个职位</posCount></Job><Job><jobTitle>爱用技术部招聘 软件测试</jobTitle><jobSaray>5-6K/月</jobSaray><jobDemand>上海市 本科 应届生</jobDemand><commpanyName>上海爱用宝科技股份有限公司</commpanyName><commpanyDesc>无</commpanyDesc><posCount>4个职位</posCount></Job><Job><jobTitle>PHP高级工程师 P6</jobTitle><jobSaray>15-25K/月</jobSaray><jobDemand>上海市 本科 5-10年</jobDemand><commpanyName>上海爱用宝科技股份有限公司</commpanyName><commpanyDesc>无</commpanyDesc><posCount>4个职位</posCount></Job><Job><jobTitle>React Web前端实习</jobTitle><jobSaray>5-6K/月</jobSaray><jobDemand>上海市 本科 应届生</jobDemand><commpanyName>上海爱用宝科技股份有限公司</commpanyName><commpanyDesc>无</commpanyDesc><posCount>4个职位</posCount></Job><Job><jobTitle>IC测试部部长</jobTitle><jobSaray>25-35K/月</jobSaray><jobDemand>深圳市 本科 5-10年</jobDemand><commpanyName>锐仕方达（北京）人力资源顾问有限公司</commpanyName><commpanyDesc>定期体检 通讯补贴 餐饮补贴 补充医疗保险 五险一金</commpanyDesc><posCount>17个职位</posCount></Job><Job><jobTitle>资深系统测试工程师</jobTitle><jobSaray>25-35K/月</jobSaray><jobDemand>深圳市 本科 5-10年</jobDemand><commpanyName>锐仕方达（北京）人力资源顾问有限公司</commpanyName><commpanyDesc>项目奖金 国内知名存储企业</commpanyDesc><posCount>17个职位</posCount></Job><Job><jobTitle>Web前端工程师</jobTitle><jobSaray>25-30K/月</jobSaray><jobDemand>北京市 本科 3-5年</jobDemand><commpanyName>天津数加科技有限公司</commpanyName><commpanyDesc>年终奖金 五险一金</commpanyDesc><posCount>6个职位</posCount></Job><Job><jobTitle>C/C++中级研发工程师</jobTitle><jobSaray>10-20K/月</jobSaray><jobDemand>上海市 本科 1-3年</jobDemand><commpanyName>上海弘连网络科技有限公司</commpanyName><commpanyDesc>无</commpanyDesc><posCount>10个职位</posCount></Job><Job><jobTitle>软件逆向分析工程师</jobTitle><jobSaray>8-16K/月</jobSaray><jobDemand>上海市 本科 1-3年</jobDemand><commpanyName>上海弘连网络科技有限公司</commpanyName><commpanyDesc>无</commpanyDesc><posCount>10个职位</posCount></Job><Job><jobTitle>前端开发工程师</jobTitle><jobSaray>9-15K/月</jobSaray><jobDemand>上海市 本科 1-3年</jobDemand><commpanyName>上海弘连网络科技有限公司</commpanyName><commpanyDesc>无</commpanyDesc><posCount>10个职位</posCount></Job><Job><jobTitle>测试工程师</jobTitle><jobSaray>6-10K/月</jobSaray><jobDemand>上海市 本科 1-3年</jobDemand><commpanyName>上海弘连网络科技有限公司</commpanyName><commpanyDesc>无</commpanyDesc><posCount>10个职位</posCount></Job><Job><jobTitle>GO语言初级研发人员</jobTitle><jobSaray>8-12K/月</jobSaray><jobDemand>上海市 本科 1-3年</jobDemand><commpanyName>上海弘连网络科技有限公司</commpanyName><commpanyDesc>无</commpanyDesc><posCount>10个职位</posCount></Job><Job><jobTitle>C# 研发工程师</jobTitle><jobSaray>10-20K/月</jobSaray><jobDemand>上海市 本科 1-3年</jobDemand><commpanyName>上海弘连网络科技有限公司</commpanyName><commpanyDesc>无</commpanyDesc><posCount>10个职位</posCount></Job><Job><jobTitle>ASP.NET工程师</jobTitle><jobSaray>10-20K/月</jobSaray><jobDemand>上海市 本科 1-3年</jobDemand><commpanyName>上海弘连网络科技有限公司</commpanyName><commpanyDesc>无</commpanyDesc><posCount>10个职位</posCount></Job><Job><jobTitle>C++/GO语言/研发工程师</jobTitle><jobSaray>8-15K/月</jobSaray><jobDemand>上海市 本科 1-3年</jobDemand><commpanyName>上海弘连网络科技有限公司</commpanyName><commpanyDesc>无</commpanyDesc><posCount>10个职位</posCount></Job><Job><jobTitle>取证/安全专家</jobTitle><jobSaray>10-20K/月</jobSaray><jobDemand>上海市 本科 1-3年</jobDemand><commpanyName>上海弘连网络科技有限公司</commpanyName><commpanyDesc>无</commpanyDesc><posCount>10个职位</posCount></Job><Job><jobTitle>前端开发工程师</jobTitle><jobSaray>4-6K/月</jobSaray><jobDemand>北京市 本科 应届生</jobDemand><commpanyName>北京天地益星通信软件有限公司</commpanyName><commpanyDesc>无</commpanyDesc><posCount>3个职位</posCount></Job><Job><jobTitle>高级PHP开发工程师</jobTitle><jobSaray>20-30K/月</jobSaray><jobDemand>深圳市 本科 3-5年</jobDemand><commpanyName>深圳盈富斯科技有限公司</commpanyName><commpanyDesc>国内top跨境电商 红杉+IDG联手三亿 甲骨文大数据大牛带队 妹纸颜值超高</commpanyDesc><posCount>2个职位</posCount></Job><Job><jobTitle>前端工程师-跨境电商</jobTitle><jobSaray>20-30K/月</jobSaray><jobDemand>深圳市 本科 3-5年</jobDemand><commpanyName>深圳盈富斯科技有限公司</commpanyName><commpanyDesc>国内Top电商企业</commpanyDesc><posCount>2个职位</posCount></Job><Job><jobTitle>ETL开发工程师</jobTitle><jobSaray>15-20K/月</jobSaray><jobDemand>北京市 本科 1-3年</jobDemand><commpanyName>思德商务信息咨询（天津）有限公司</commpanyName><commpanyDesc>15薪 补贴 甲方职位 四惠东</commpanyDesc><posCount>5个职位</posCount></Job><Job><jobTitle>数据库开发工程师</jobTitle><jobSaray>18-27K/月</jobSaray><jobDemand>北京市 本科 3-5年</jobDemand><commpanyName>思德商务信息咨询（天津）有限公司</commpanyName><commpanyDesc>15薪 补贴 甲方职位 四惠东</commpanyDesc><posCount>5个职位</posCount></Job><Job><jobTitle>高级Java开发工程师</jobTitle><jobSaray>20-30K/月</jobSaray><jobDemand>北京市 本科 3-5年</jobDemand><commpanyName>思德商务信息咨询（天津）有限公司</commpanyName><commpanyDesc>15薪 补贴 甲方职位 四惠东</commpanyDesc><posCount>5个职位</posCount></Job><Job><jobTitle>APP测试工程师</jobTitle><jobSaray>18-25K/月</jobSaray><jobDemand>北京市 本科 3-5年</jobDemand><commpanyName>思德商务信息咨询（天津）有限公司</commpanyName><commpanyDesc>15薪 补贴 甲方职位 四惠东</commpanyDesc><posCount>5个职位</posCount></Job><Job><jobTitle>Android开发工程师</jobTitle><jobSaray>15-25K/月</jobSaray><jobDemand>北京市 本科 3-5年</jobDemand><commpanyName>思德商务信息咨询（天津）有限公司</commpanyName><commpanyDesc>15薪 补贴 甲方职位 四惠东</commpanyDesc><posCount>5个职位</posCount></Job><Job><jobTitle>阿里游戏-游戏客户端开发工程师</jobTitle><jobSaray>15-25K/月</jobSaray><jobDemand>广州市 本科 3-5年</jobDemand><commpanyName>阿里巴巴集团</commpanyName><commpanyDesc>有竞争力的薪酬 尊重个人发展意愿</commpanyDesc><posCount>52个职位</posCount></Job><Job><jobTitle>阿里游戏-游戏服务端开发工程师</jobTitle><jobSaray>15-25K/月</jobSaray><jobDemand>广州市 本科 3-5年</jobDemand><commpanyName>阿里巴巴集团</commpanyName><commpanyDesc>尊重个人发展意愿 有竞争力的薪酬</commpanyDesc><posCount>52个职位</posCount></Job><Job><jobTitle>阿里游戏-平台WEB前端工程师</jobTitle><jobSaray>15-30K/月</jobSaray><jobDemand>广州市 本科 3-5年</jobDemand><commpanyName>阿里巴巴集团</commpanyName><commpanyDesc>有竞争力的薪酬 尊重个人发展意愿</commpanyDesc><posCount>52个职位</posCount></Job><Job><jobTitle>阿里游戏-游戏测试（广州/深圳/上海）</jobTitle><jobSaray>15-25K/月</jobSaray><jobDemand>广州市 本科 3-5年</jobDemand><commpanyName>阿里巴巴集团</commpanyName><commpanyDesc>浓厚的技术氛围</commpanyDesc><posCount>52个职位</posCount></Job><Job><jobTitle>阿里游戏-引擎开发专家</jobTitle><jobSaray>15-30K/月</jobSaray><jobDemand>广州市 本科 3-5年</jobDemand><commpanyName>阿里巴巴集团</commpanyName><commpanyDesc>完善的培训体系 晋升空间 优秀的引擎团队 有竞争力的薪酬 尊重个人发展意愿</commpanyDesc><posCount>52个职位</posCount></Job><Job><jobTitle>SLAM 与三维视觉工程师 /专家</jobTitle><jobSaray>20-40K/月</jobSaray><jobDemand>杭州市 硕士 1-3年</jobDemand><commpanyName>阿里巴巴集团</commpanyName><commpanyDesc>优秀人才阿里股票 有竞争力的薪酬 主流算法研究方向 尊重个人发展意愿</commpanyDesc><posCount>52个职位</posCount></Job><Job><jobTitle>React Web前端开发工程师</jobTitle><jobSaray>10-15K/月</jobSaray><jobDemand>上海市 本科 1-3年</jobDemand><commpanyName>上海爱用宝科技股份有限公司</commpanyName><commpanyDesc>无</commpanyDesc><posCount>4个职位</posCount></Job><Job><jobTitle>Node.js研发工程师</jobTitle><jobSaray>9-18K/月</jobSaray><jobDemand>上海市 本科 1-3年</jobDemand><commpanyName>上海弘连网络科技有限公司</commpanyName><commpanyDesc>无</commpanyDesc><posCount>10个职位</posCount></Job><Job><jobTitle>Python开发实习生</jobTitle><jobSaray>4-8K/月</jobSaray><jobDemand>北京市 本科 应届生</jobDemand><commpanyName>天津数加科技有限公司</commpanyName><commpanyDesc>无</commpanyDesc><posCount>6个职位</posCount></Job><Job><jobTitle>人力资源主管</jobTitle><jobSaray>6-10K/月</jobSaray><jobDemand>北京市 大专 1-3年</jobDemand><commpanyName>天津数加科技有限公司</commpanyName><commpanyDesc>年终奖金 五险一金</commpanyDesc><posCount>6个职位</posCount></Job><Job><jobTitle>社区运营经理</jobTitle><jobSaray>15-20K/月</jobSaray><jobDemand>北京市 本科 1-3年</jobDemand><commpanyName>天津数加科技有限公司</commpanyName><commpanyDesc>年终奖金 五险一金</commpanyDesc><posCount>6个职位</posCount></Job><Job><jobTitle>区块链后端研发工程师</jobTitle><jobSaray>30-35K/月</jobSaray><jobDemand>北京市 本科 1-3年</jobDemand><commpanyName>天津数加科技有限公司</commpanyName><commpanyDesc>年终奖金 五险一金</commpanyDesc><posCount>6个职位</posCount></Job><Job><jobTitle>区块链产品经理</jobTitle><jobSaray>25-30K/月</jobSaray><jobDemand>北京市 本科 3-5年</jobDemand><commpanyName>天津数加科技有限公司</commpanyName><commpanyDesc>年终奖金 五险一金</commpanyDesc><posCount>6个职位</posCount></Job><Job><jobTitle>前端开发工程师</jobTitle><jobSaray>8-15K/月</jobSaray><jobDemand>杭州市 本科 1-3年</jobDemand><commpanyName>杭州基智基因科技有限公司</commpanyName><commpanyDesc>核心项目 技术大牛 五险一金 薪资不设限 行业翘楚</commpanyDesc><posCount>4个职位</posCount></Job><Job><jobTitle>c/c++开发工程师</jobTitle><jobSaray>10-15K/月</jobSaray><jobDemand>南京市 本科 1-3年</jobDemand><commpanyName>亚信科技(中国)有限公司</commpanyName><commpanyDesc>超多年假 技能培训 年底双薪 年终奖金</commpanyDesc><posCount>1个职位</posCount></Job><Job><jobTitle>自然语言处理师</jobTitle><jobSaray>15-30K/月</jobSaray><jobDemand>成都市 本科 1-3年</jobDemand><commpanyName>成都市晓易互动科技有限公司</commpanyName><commpanyDesc>定期体检 周末双休</commpanyDesc><posCount>9个职位</posCount></Job><Job><jobTitle>销售</jobTitle><jobSaray>6-12K/月</jobSaray><jobDemand>上海市 大专 1年以下</jobDemand><commpanyName>上海普加软件有限公司</commpanyName><commpanyDesc>定期体检 节日福利 每年多次调薪 年底双薪 五险一金</commpanyDesc><posCount>6个职位</posCount></Job><Job><jobTitle>文案编辑</jobTitle><jobSaray>8-15K/月</jobSaray><jobDemand>上海市 大专 1-3年</jobDemand><commpanyName>上海普加软件有限公司</commpanyName><commpanyDesc>定期体检 节日福利 每年多次调薪 年底双薪 五险一金</commpanyDesc><posCount>6个职位</posCount></Job><Job><jobTitle>销售经理/主管</jobTitle><jobSaray>8-15K/月</jobSaray><jobDemand>上海市 大专 3-5年</jobDemand><commpanyName>上海普加软件有限公司</commpanyName><commpanyDesc>定期体检 节日福利 每年多次调薪 年底双薪 五险一金</commpanyDesc><posCount>6个职位</posCount></Job><Job><jobTitle>项目管理实施顾问（P6/MS Proje...</jobTitle><jobSaray>10-15K/月</jobSaray><jobDemand>上海市 本科 3-5年</jobDemand><commpanyName>上海普加软件有限公司</commpanyName><commpanyDesc>定期体检 节日福利 每年多次调薪 年底双薪 五险一金</commpanyDesc><posCount>6个职位</posCount></Job><Job><jobTitle>Java高级工程师</jobTitle><jobSaray>15-20K/月</jobSaray><jobDemand>上海市 大专 5-10年</jobDemand><commpanyName>上海普加软件有限公司</commpanyName><commpanyDesc>每年多次调薪 节日福利 定期体检 年底双薪 五险一金</commpanyDesc><posCount>6个职位</posCount></Job><Job><jobTitle>web前端开发工程师</jobTitle><jobSaray>8-10K/月</jobSaray><jobDemand>深圳市 大专 1-3年</jobDemand><commpanyName>深圳普华春天科技发展有限公司</commpanyName><commpanyDesc>定期体检 绩效奖金 节日福利 年底双薪 五险一金</commpanyDesc><posCount>3个职位</posCount></Job><Job><jobTitle>ASP.NET工程师</jobTitle><jobSaray>8-13K/月</jobSaray><jobDemand>深圳市 大专 1-3年</jobDemand><commpanyName>深圳普华春天科技发展有限公司</commpanyName><commpanyDesc>绩效奖金 定期体检 五险一金 节日福利 年底双薪</commpanyDesc><posCount>3个职位</posCount></Job><Job><jobTitle>安卓开发工程师</jobTitle><jobSaray>5-10K/月</jobSaray><jobDemand>梧州市 本科 1-3年</jobDemand><commpanyName>梧州游易网络科技有限公司</commpanyName><commpanyDesc>无</commpanyDesc><posCount>1个职位</posCount></Job><Job><jobTitle>JAVA开发工程师</jobTitle><jobSaray>9-11K/月</jobSaray><jobDemand>深圳市 大专 1-3年</jobDemand><commpanyName>深圳普华春天科技发展有限公司</commpanyName><commpanyDesc>定期体检 绩效奖金 节日福利 年底双薪 五险一金</commpanyDesc><posCount>3个职位</posCount></Job><Job><jobTitle>区块链底层服务研发工程师</jobTitle><jobSaray>15-30K/月</jobSaray><jobDemand>杭州市 大专 3-5年</jobDemand><commpanyName>北京思拓客网络科技有限公司</commpanyName><commpanyDesc>高薪</commpanyDesc><posCount>4个职位</posCount></Job><Job><jobTitle>区块链dapp及智能合约开发工程师</jobTitle><jobSaray>15-30K/月</jobSaray><jobDemand>杭州市 大专 3-5年</jobDemand><commpanyName>北京思拓客网络科技有限公司</commpanyName><commpanyDesc>高薪</commpanyDesc><posCount>4个职位</posCount></Job><Job><jobTitle>中、高级java开发工程师</jobTitle><jobSaray>15-30K/月</jobSaray><jobDemand>北京市 本科 3-5年</jobDemand><commpanyName>北京易宝支付有限公司</commpanyName><commpanyDesc>弹性工作-不打卡 年轻化的团队-高薪</commpanyDesc><posCount>2个职位</posCount></Job><Job><jobTitle>高级前端开发工程师</jobTitle><jobSaray>15-30K/月</jobSaray><jobDemand>北京市 本科 5-10年</jobDemand><commpanyName>北京易宝支付有限公司</commpanyName><commpanyDesc>六险一金-大平台</commpanyDesc><posCount>2个职位</posCount></Job><Job><jobTitle>区块链运维工程师</jobTitle><jobSaray>15-30K/月</jobSaray><jobDemand>杭州市 本科 3-5年</jobDemand><commpanyName>北京思拓客网络科技有限公司</commpanyName><commpanyDesc>高薪</commpanyDesc><posCount>4个职位</posCount></Job><Job><jobTitle>区块链产品经理</jobTitle><jobSaray>15-30K/月</jobSaray><jobDemand>杭州市 本科 3-5年</jobDemand><commpanyName>北京思拓客网络科技有限公司</commpanyName><commpanyDesc>无</commpanyDesc><posCount>4个职位</posCount></Job><Job><jobTitle>.net软件工程师</jobTitle><jobSaray>10-20K/月</jobSaray><jobDemand>上海市 本科 3-5年</jobDemand><commpanyName>潍柴动力股份有限公司上海研发中心</commpanyName><commpanyDesc>无</commpanyDesc><posCount>2个职位</posCount></Job><Job><jobTitle>车联网软件工程师</jobTitle><jobSaray>15-20K/月</jobSaray><jobDemand>上海市 本科 3-5年</jobDemand><commpanyName>潍柴动力股份有限公司上海研发中心</commpanyName><commpanyDesc>无</commpanyDesc><posCount>2个职位</posCount></Job><Job><jobTitle>系统管理员</jobTitle><jobSaray>13-25K/月</jobSaray><jobDemand>深圳市 本科 3-5年</jobDemand><commpanyName>平安科技(深圳)有限公司</commpanyName><commpanyDesc>无</commpanyDesc><posCount>5个职位</posCount></Job><Job><jobTitle>数据库管理员（DBA)</jobTitle><jobSaray>13-25K/月</jobSaray><jobDemand>深圳市 本科 3-5年</jobDemand><commpanyName>平安科技(深圳)有限公司</commpanyName><commpanyDesc>无</commpanyDesc><posCount>5个职位</posCount></Job><Job><jobTitle>应用运维工程师</jobTitle><jobSaray>14-28K/月</jobSaray><jobDemand>深圳市 本科 3-5年</jobDemand><commpanyName>平安科技(深圳)有限公司</commpanyName><commpanyDesc>无</commpanyDesc><posCount>5个职位</posCount></Job><Job><jobTitle>应用平台工程师</jobTitle><jobSaray>15-28K/月</jobSaray><jobDemand>深圳市 本科 3-5年</jobDemand><commpanyName>平安科技(深圳)有限公司</commpanyName><commpanyDesc>无</commpanyDesc><posCount>5个职位</posCount></Job></jobs>
